Workbook
Name ACOPLE_BRIDADO: 'P. PARTES'!$A$266:$A$322
Name ACOPLE_DIRECTO: 'P. PARTES'!$A$239:$A$263
Name EJE_MACIZO: 'P. PARTES'!$A$325:$A$376
Name EJE_TUBULAR: 'P. PARTES'!$A$379:$A$434
Name MOTOREDUCTOR: 'P. PARTES'!$A$457:$A$563
Name NO_APLICA: 'P. PARTES'!$E$607:$E$612
Name PERNOS: 'P. PARTES'!$A$566:$A$568
Name PLACA: 'P. PARTES'!$A$571
Name PLETINAS: 'P. PARTES'!$A$437:$A$454
Name PROPELAS: 'P. PARTES'!$A$3:$A$236

Sheet CODIFICADOR
A1: CODIFICACION DE PARTES DE AGITADOR
G3: P3-LICS
A4: CODIFICACION EJE
A6: SELECCIONAR TIPO DE ACOPLE | B6: SELECCIONAR SCHEDULE | C6: ESCRIBA LONGITUD EN mm | D6: SELECCIONAR DIAMETRO | E6: SELECCIONAR MATERIAL | G6: CODIGO
A7: BRIDADO | B7: MACIZO | C7: 1700 | D7: (2") | E7: Acero 316SS | G7: =CONCATENATE("EJ",VLOOKUP(A7,'HERR CODS'!C2:D3,2,0),VLOOKUP(B7,'HERR CODS'!E2:F5,2,0),IF(C7/10<100,CONCATENATE("0",C7/10),C7/10),VLOOKUP(D7,'HERR CODS'!I2:J14,2,0),VLOOKUP(E7,'HERR CODS'!K2:L4,2,0)) -> EJBA170ES
G8: =IF(COUNTIF('P. PARTES'!$A$4:$C$604,CODIFICADOR!G7)=1,"SI","NO") -> NO
A10: CODIFICACION ACOPLE BRIDADO
G11: CODIGO
A12: SELECCIONAR DIAMETRO DE AGITADOR | B12: SELECCIONAR DIAMETRO DE EJE MOTOREDUCTOR (mm) | C12: SELECCIONAR MATERIAL | G12: =CONCATENATE("AB-",VLOOKUP(A13,'HERR CODS'!B24:C29,2,0),"-",VLOOKUP(B13,'HERR CODS'!P24:Q36,2,0),VLOOKUP(C13,'HERR CODS'!H70:I74,2,0)) -> AB-2-30
A13: 2" | B13: 30 | C13: ACERO 304SS | G13: =IF(COUNTIF('P. PARTES'!$A$4:$C$604,CODIFICADOR!G12)=1,"SI","NO") -> SI
A16: CODIFICACION ACOPLE DIRECTO
G17: CODIGO
A18: SELECCIONAR DIAMETRO DE EJE MOTOREDUCTOR (mm) | B18: SELECCIONAR DIAMETRO DE AGITADOR | C18: SELECCIONAR MATERIAL | G18: =CONCATENATE("AD-",VLOOKUP(A19,'HERR CODS'!E24:F36,2,0),"-",VLOOKUP(B19,'HERR CODS'!B72:C75,2,0),VLOOKUP(C19,'HERR CODS'!H70:I74,2,0)) -> #N/A
G19: EXISTE?
G20: =IF(COUNTIF('P. PARTES'!$A$4:$C$604,CODIFICADOR!G18)=1,"SI","NO") -> NO
A22: CODIFICACION PROPELA
G23: CODIGO
A24: SELECCIONAR TIPO DE PROPELA | B24: SELECCIONAR DIAMETRO DE PROPELA (mm) | C24: SELECCIONAR DIAMETRO DE EJE | D24: SELECCIONAR TIPO DE AJUSTE AL EJE | E24: SELECCIONAR MATERIAL | G24: =CONCATENATE("P",VLOOKUP(A25,'HERR CODS'!A40:B49,2,0),"-",VLOOKUP(B25,'HERR CODS'!D40:E64,2,0),VLOOKUP(C25,'HERR CODS'!G40:H53,2,0),VLOOKUP(D25,'HERR CODS'!I40:J42,2,0),VLOOKUP(E25,'HERR CODS'!M40:N42,2,0)) -> P2-GEMS
A25: TURBINA | B25: 500 | C25: (2") | D25: MANZANA | E25: Acero inoxidable 316SS | G25: EXISTE?
G26: =IF(COUNTIF('P. PARTES'!$A$3:$C$604,CODIFICADOR!G24)=1,"SI","NO") -> SI
A29: CODIFICACION AGITADOR
B31: PROPELA TIPO 1 (DE ABAJO HACIA ARRIBA)
A32: SELECCIONAR TIPO | B32: TIPO DE PROPELAS | C32: NÚMERO DE PROPELAS | D32: DIAMETRO (mm)
A33: VERTICAL | B33: CURVA TRIPALA - CT | C33: 1 | D33: 500
B35: PROPELA TIPO 2 (DE ARRIBA HACIA ABAJO)
B36: TIPO DE PROPELAS | C36: NÚMERO DE PROPELAS | D36: DIAMETRO
B37: NO APLICA | C37: NO APLICA | D37: NO APLICA | G37: CODIGO
G38: =CONCATENATE(VLOOKUP(A33,'HERR CODS'!A83:B84,2,0),VLOOKUP(B33,'HERR CODS'!C91:D101,2,0),VLOOKUP(C33,'HERR CODS'!E92:F96,2,0),VLOOKUP(D33,'HERR CODS'!G102:H128,2,0),VLOOKUP(B37,'HERR CODS'!C91:D101,2,0),IF(B37="NO APLICA",,VLOOKUP(C37,'HERR CODS'!E92:F96,2,0)),IF(B37="NO APLICA","-",VLOOKUP(D37,'HERR CODS'!G102:H128,2,0)),IF(B40/100<10,CONCATENATE("0",B40/100),B40/100),VLOOKUP(C40,'HERR CODS'!Q103:R124,2,0),IF(D40<100,CONCATENATE("0",D40),D40),VLOOKUP(B44,'HERR CODS'!U90:V91,2,0),VLOOKUP(C44,'HERR CODS'!W90:X95,2,0),VLOOKUP(CODIFICADOR!D44,'HERR CODS'!Y90:Z91,2,0),VLOOKUP(CODIFICADOR!B46,'HERR CODS'!AA90:AB91,2,0),VLOOKUP(CODIFICADOR!C46,'HERR CODS'!AC90:AD93,2,0),VLOOKUP(D46,'HERR CODS'!AE89:AF95,2,0)) -> V3AF-08G090 | AI38: =CONCATENATE(VLOOKUP(AC33,'HERR CODS'!AC83:AD84,2,0),VLOOKUP(AD33,'HERR CODS'!AE91:AF101,2,0),VLOOKUP(AE33,'HERR CODS'!AG92:AH96,2,0),VLOOKUP(AF33,'HERR CODS'!AI102:AJ128,2,0),VLOOKUP(AD37,'HERR CODS'!AE91:AF101,2,0),IF(AD37="NO APLICA",,VLOOKUP(AE37,'HERR CODS'!AG92:AH96,2,0)),IF(AD37="NO APLICA","-",VLOOKUP(AF37,'HERR CODS'!AI102:AJ128,2,0)),IF(AD40/100<10,CONCATENATE("0",AD40/100),AD40/100),VLOOKUP(AE40,'HERR CODS'!AS103:AT124,2,0),IF(AF40<100,CONCATENATE("0",AF40),AF40),VLOOKUP(AD44,'HERR CODS'!AW90:AX91,2,0),VLOOKUP(AE44,'HERR CODS'!AY90:AZ95,2,0),VLOOKUP(CODIFICADOR!AF44,'HERR CODS'!BA90:BB91,2,0),VLOOKUP(CODIFICADOR!AD46,'HERR CODS'!BC90:BD91,2,0),VLOOKUP(CODIFICADOR!AE46,'HERR CODS'!BE90:BF93,2,0),VLOOKUP(AF46,'HERR CODS'!BG89:BH94,2,0)) -> #N/A
B39: ESCRIBA LONGITUD EJE EN mm | C39: POTENCIA (Kw) | D39: ESCRIBA VELOCIDAD (rpm)
B40: 800 | C40: 2.2 | D40: 90
B42: ADICIONALES
B43: MANEJO VELOCIDAD | C43: ELEMENTO MOTRIZ | D43: LINTERNA
B44: VELOCIDAD REDUCIDA | C44: TRIFASICO | D44: Sin linterna
B45: SELLO | C45: MATERIAL | D45: ACABADO - RECUBRIMIENTO
B46: Sin sello | C46: 304SS | D46: NINGUNO
D56: =2.44/3 -> 0.81333333

Sheet PLANTILLA DE P.  (2)
I1: NOTAS DE SELECCIÓN
A2: MODELO DEL AGITADOR: | E2: FECHA | G2: ELABORO
B4: CÓDIGO | C4: DESCRIPCIÓN PIEZA | D4: CANT | G4: VALOR PARCIAL
A5: MOTOREDUCTOR | B5: SK5721IEC90SK90L4 | C5: MOTORREDUTOR 2.2 KW // 90 RPM//SK5721IEC100C20 | D5: 1 | E5: 5378000 | G5: =E5 -> 5378000 | H5: NORD | Q5: =NOT(R5) -> FALSE | R5: =COUNTIF(INDIRECT(A5),B5) -> 1
C6: LITERNA DE RODAMIENTOS | D6: 0 | E6: 9000000 | G6: =E6*D6 -> 0
A7: PROPELAS | B7: P3-GDC | C7: =VLOOKUP(B7,'P. PARTES'!$A$3:C689,3,0) -> Propela Tripala 500 mm eje 1 1/2" con casquete 304SS | D7: 1 | E7: 700000 | G7: =E7*D7 -> 700000
A8: ACOPLE_DIRECTO | B8: AD-025-038 | C8: =VLOOKUP(B8,'P. PARTES'!$A$3:C689,3,0) -> Acople directo EJE AG 1 1/2" EJE MR 25 mm 304SS | D8: 1 | E8: 380000 | G8: =E8*D8 -> 380000
A9: EJE_MACIZO | B9: EJDA100D | C9: =VLOOKUP(B9,'P. PARTES'!$A$3:C690,3,0) -> Eje macizo 1 1/2" 500 - 1000 mm 304SS | D9: 1 | E9: 400000 | G9: =E9*D9 -> 400000 | I9: Sujeta a cambios dependiendo el tamaño del eje del MR | Q9: =NOT(R9) -> FALSE | R9: =COUNTIF(INDIRECT(A9),B9) -> 1
A10: PLETINAS | B10: PL-210-516-110 | C10: =VLOOKUP(B10,'P. PARTES'!$A$3:C691,3,0) -> Pletina cuadrada de 210 mm * 5/16" A36 GALVANIZADO | D10: 1 | E10: 250000 | G10: =E10*D10 -> 250000 | Q10: =NOT(R10) -> FALSE | R10: =COUNTIF(INDIRECT(A10),B10) -> 1
A11: PERNOS | B11: PERNOS AG PEQUEÑO | C11: Para | D11: 1 | E11: 20000 | G11: =E11*D11 -> 20000 | Q11: =NOT(R11) -> FALSE | R11: =COUNTIF(INDIRECT(A11),B11) -> 1
A12: PLACA | B12: PLACAS AG. | C12: PLACA | D12: 1 | E12: 52000 | G12: =E12*D12 -> 52000 | Q12: =NOT(R12) -> FALSE | R12: =COUNTIF(INDIRECT(A12),B12) -> 1
A13: OTROS | C13: EMPAQUE (MADERA) | D13: 1 | E13: 150000 | G13: =E13*D13 -> 150000 | Q13: =NOT(R13) -> #REF! | R13: =COUNTIF(INDIRECT(A13),B13) -> #REF!
A14: OTROS | C14: EMPAQUE (MANO DE OBRA) | D14: 1 | E14: 150000 | G14: =E14*D14 -> 150000
A15: OTROS | C15: PRUEBAS y DOCUMENTACION | D15: 0 | E15: 300000 | G15: =E15*D15 -> 0
A16: OTROS | C16: PINTURA | D16: 0 | E16: 200000 | G16: =E16*D16 -> 0 | M16: MARGEN | Q16: =NOT(R16) -> #REF! | R16: =COUNTIF(INDIRECT(A16),B16) -> #REF!
A17: OTROS | B17: OTROS | C17: RECUBRIMIENTO | D17: 0 | E17: 8000000 | G17: =E17*D17 -> 0
A18: OTROS | B18: OTROS | C18: ACOMPAÑAMIENTO EN ARRANQUE Y PRUEBAS | D18: 1 | E18: 2300000 | G18: =E18*D18 -> 2300000
D19: Subtotal materiales | G19: =SUM(G5:G18) -> 9780000 | K19: =G23/L19 -> 21750720 | L19: 0.5 | M19: 0.5
A20: DÓLAR | B20: 3650 | D20: Imprevistos | F20: 0.05 | G20: =G19*F20 -> 489000 | K20: =K19/B20 -> 5959.1014 | L20: 4000
D21: Gastos administrativos | F21: 0.05 | G21: =(G19*F21) -> 489000 | H21: T.PAGO/MESES
D22: Gastos financieros | F22: 0.012 | G22: =G19*F22*H22 -> 117360 | H22: 1
D23: Subtotal | G23: =SUM(G19:G22) -> 10875360
D24: Margen | F24: 0.4 | G24: =G23*F24 -> 4350144 | K24: 15300 | L24: usd
D25: Total COP | G25: =G23+G24 -> 15225504 | J25: =#REF!*I25 -> #REF!
D26: Total USD | G26: =G25/B20 -> 4171.371
D27: Valor de venta COP | G27: =ROUND(G25,-4) -> 15230000
D28: Valor de venta USD | G28: =ROUND(G26,-1) -> 4170
L30: 2023 | N30: INCREMENTO
L31: =K19 -> 21750720 | M31: COP | N31: =(L31-K31)/K31 -> #DIV/0!
L32: =K24 -> 15300 | M32: USD | N32: =(L32-K32)/K32 -> #DIV/0!
AF38: SI | AH38: 1
AF39: NO | AH39: 1.19
C76: MARGEN GLOBAL BASE MATERIALES
C77: =(G24+#REF!+#REF!+#REF!)/#REF! -> #REF!

Sheet Hoja1
A1: PROPELA P5-SGC
B2: Descripción | C2: Área m2 | D2: Cantidad | E2: Área total | F2: Material | G2: Peso kg | H2: Costo por kg | I2: 35000
A3: LÁMINAS | B3: Ruana | C3: =(106/1000*160/1000) -> 0.01696 | D3: 2 | E3: =D3*C3 -> 0.03392 | F3: 304ss
B4: Casquete plano | C4: =91/1000*300/1000 -> 0.0273 | D4: 4 | E4: =D4*C4 -> 0.1092 | F4: 304ss
B5: Casquete curvo | C5: =(300/1000*182/1000) -> 0.0546 | D5: 2 | E5: =D5*C5 -> 0.1092 | F5: 304ss
B6: Atiezador | C6: =(530/1000*24/1000) -> 0.01272 | D6: 2 | E6: =D6*C6 -> 0.02544 | F6: 304ss
B7: Aspa | C7: =(770/1000*270/1000) -> 0.2079 | D7: 2 | E7: =D7*C7 -> 0.4158 | F7: 304ss
D8: Área total m2 | E8: =SUM(E3:E7) -> 0.69356 | F8: 304ss
D9: Peso total kg | G9: 44.35
D10: Costo total COP | H10: =I2*G9 -> 1552250
A13: SERVICIO | B13: 990000
A15: COSTO PROPELA | B15: =H10+B13 -> 2542250

Sheet V2
A1: V2AB-06A137 | E1: V2AI-16E072 | I1: V2AI-24H108
A2: Elemento | B2: Precio | C2: PESO (KG) | E2: Elemento | F2: Precio | G2: PESO (KG) | I2: Elemento | J2: Precio | K2: PESO (KG)
A3: MR 0.25kW @ 140,4 RPM SK0721IEC71SK71S4 | B3: =INSUMOS!B524 -> 850000 | C3: =INSUMOS!E524 -> 9 | E3: MR 1,1kW @ 72 RPM SK5721IEC90SK90S4 | F3: =INSUMOS!B526 -> 1400000 | G3: =INSUMOS!E527 -> 29 | I3: MR 3kW @ 108RPM SK7721IEC100SK100LA4 | J3: =INSUMOS!B529 -> 2260000 | K3: =INSUMOS!E529 -> 87
A4: Pletina 210 * 1/4" | B4: =INSUMOS!B112 -> 96000 | C4: =INSUMOS!E112 -> 2.1982747 | E4: Pletina 210 * 1/4" | F4: =INSUMOS!B112 -> 96000 | G4: =INSUMOS!E112 -> 2.1982747 | I4: Pletina 350 * 1/4" | J4: =INSUMOS!B117 -> 115000 | K4: =INSUMOS!E117 -> 6.1063187
A5: EJE EJDA065B | B5: =EJXA!D5 -> 85350 | C5: =EJXA!E5 -> 2.5854749 | E5: EJE EJDA160E | F5: =EJXA!D33 -> 323400 | G5: =EJXA!E33 -> 25.456984 | I5: EJE EJBC240G | J5: =EJXC!D6 -> 1711923 | K5: =EJXC!E6 -> 32.05
A6: ACOPLE AD-020-025 | B6: =AD!D5 -> 197400 | C6: =AD!E5 -> 1.7899442 | E6: ACOPLE AD-035-050 | F6: =AD!D25 -> 358200 | G6: =AD!E39 -> 7.1597767 | I6: ACOPLE AB-3-040 | J6: =AB!D27 -> 546265 | K6: =AB!E27 -> 9.0468716
A7: PROPELA P2-BBM | B7: =P!D8 -> 391250 | C7: =P!E8 -> 2.3124581 | E7: PROPELA P2-JEM | F7: =P!D128 -> 779150 | G7: =P!E128 -> 21.999833 | I7: PROPELA P2-JGC | J7: =P!D157 -> 770000 | K7: =P!E157 -> 22.63
A8: PLACAS | B8: =INSUMOS!B537 -> 50000 | E8: PLACAS | F8: =INSUMOS!B537 -> 50000 | I8: PLACAS | J8: =INSUMOS!B537 -> 50000
A9: TORNILLOS AG PEQUEÑO | B9: =INSUMOS!B534 -> 50000 | C9: =INSUMOS!E534 -> 3 | E9: TORNILLOS AG MEDIANO | F9: =INSUMOS!B535 -> 80000 | G9: =INSUMOS!E535 -> 5 | I9: TORNILLOS AG MEDIANO | J9: =INSUMOS!B535 -> 80000 | K9: =INSUMOS!E535 -> 5
A10: TOTAL MATERIALES | B10: =SUM(B3:B9) -> 1720000 | C10: =SUM(C3:C9) -> 20.886152 | E10: TOTAL MATERIALES | F10: =SUM(F3:F9) -> 3086750 | G10: =SUM(G3:G9) -> 90.814868 | I10: TOTAL MATERIALES | J10: =SUM(J3:J9) -> 5533188 | K10: =SUM(K3:K9) -> 161.83319
A12: V2AD-09A137 | E12: V2AI-18F077 | I12: V2AJ-24H088
A13: Elemento | B13: Precio | C13: PESO (KG) | E13: Elemento | F13: Precio | G13: PESO (KG) | I13: Elemento | J13: Precio | K13: PESO (KG)
A14: MR 0.25kW @ 140,4 RPM SK0721IEC71SK71S4 | B14: =INSUMOS!B524 -> 850000 | C14: =INSUMOS!E524 -> 9 | E14: MR 1,5kW @ 76,8 RPM SK5721IEC90SK90L4 | F14: =INSUMOS!B527 -> 1410000 | G14: =INSUMOS!E526 -> 29 | I14: MR 3kW @ 88RPM SK7721IEC100SK100LA4 | J14: =INSUMOS!B529 -> 2260000 | K14: =INSUMOS!E529 -> 87
A15: Pletina 210 * 1/4" | B15: =INSUMOS!B112 -> 96000 | C15: =INSUMOS!E112 -> 2.1982747 | E15: Pletina 210 * 1/4" | F15: =INSUMOS!B112 -> 96000 | G15: =INSUMOS!E112 -> 2.1982747 | I15: Pletina 350 * 1/4" | J15: =INSUMOS!B117 -> 115000 | K15: =INSUMOS!E117 -> 6.1063187
A16: EJE EJDA090B | B16: =EJXA!D12 -> 95100 | C16: =EJXA!E12 -> 3.5798883 | E16: EJE EJDA180E | F16: =EJXA!D46 -> 354200 | G16: =EJXA!E46 -> 28.639107 | I16: EJE EJBC240G | J16: =EJXC!D6 -> 1711923 | K16: =EJXC!E6 -> 32.05
A17: ACOPLE AD-020-025 | B17: =AD!D5 -> 197400 | C17: =AD!E5 -> 1.7899442 | E17: ACOPLE AD-035-050 | F17: =AD!D25 -> 358200 | G17: =AD!E39 -> 7.1597767 | I17: ACOPLE AB-3-040 | J17: =AB!D27 -> 546265 | K17: =AB!E27 -> 9.0468716
A18: PROPELA P2-DBM | B18: =P!D18 -> 441250 | C18: =P!E18 -> 4.2524581 | E18: PROPELA P2-JEM | F18: =P!D128 -> 779150 | G18: =P!E128 -> 21.999833 | I18: PROPELA P2-kGC | J18: =P!D166 -> 850000 | K18: =P!E166 -> 30
A19: PLACAS | B19: =INSUMOS!B537 -> 50000 | E19: PLACAS | F19: =INSUMOS!B537 -> 50000 | I19: PLACAS | J19: =INSUMOS!B537 -> 50000
A20: TORNILLOS AG PEQUEÑO | B20: =INSUMOS!B534 -> 50000 | C20: =INSUMOS!E534 -> 3 | E20: TORNILLOS AG MEDIANO | F20: =INSUMOS!B535 -> 80000 | G20: =INSUMOS!E535 -> 5 | I20: TORNILLOS AG MEDIANO | J20: =INSUMOS!B535 -> 80000 | K20: =INSUMOS!E535 -> 5
A21: TOTAL | B21: =SUM(B14:B20) -> 1779750 | C21: =SUM(C14:C20) -> 23.820565 | E21: TOTAL MATERIALES | F21: =SUM(F14:F20) -> 3127550 | G21: =SUM(G14:G20) -> 93.996991 | I21: TOTAL MATERIALES | J21: =SUM(J14:J20) -> 5613188 | K21: =SUM(K14:K20) -> 169.20319
A23: V2AD-11C192 | E23: V2AJ-20B046 | I23: V2AJ-26J102
A24: Elemento | B24: Precio | C24: PESO (KG) | E24: Elemento | F24: Precio | G24: PESO (KG) | I24: Elemento | J24: Precio | K24: PESO (KG)
A25: MR 0.55kW @ 190 RPM SK1721IEC80SK80S4 | B25: =INSUMOS!B525 -> 1100000 | C25: =INSUMOS!E525 -> 13 | E25: MR 0,37kW @ 46RPM SK3721IEC71SK71L4 | F25: =INSUMOS!B528 -> 1040000 | G25: =INSUMOS!E528 -> 28 | I25: MR 5,5kW @ 102RPM SK8721IEC132SK132S4 | J25: =INSUMOS!B530 -> 4900000 | K25: =INSUMOS!E530 -> 97
A26: Pletina 210 * 1/4" | B26: =INSUMOS!B112 -> 96000 | C26: =INSUMOS!E112 -> 2.1982747 | E26: Pletina 210 * 1/4" | F26: =INSUMOS!B112 -> 96000 | G26: =INSUMOS!E112 -> 2.1982747 | I26: Pletina 350 * 3/8" | J26: =INSUMOS!B118 -> 160000 | K26: =INSUMOS!E118 -> 9.1594781
A27: EJE EJDA109C | B27: =EJXA!D19 -> 129760 | C27: =EJXA!E19 -> 6.7744415 | E27: EJE EJDA200D | F27: =EJXA!D53 -> 251000 | G27: =EJXA!E53 -> 17.899442 | I27: EJE EJBC270I | J27: =EJXC!D13 -> 2618025 | K27: =EJXC!E13 -> 50.443
A28: ACOPLE AD-020-032 | B28: =AD!D12 -> 232800 | C28: =AD!E12 -> 3.182123 | E28: ACOPLE AD-025-038 | F28: =AD!D32 -> 232800 | G28: =AD!E32 -> 3.182123 | I28: ACOPLE AB-4-050 | J28: =AB!D13 -> 647320 | K28: =AB!E13 -> 15.909944
A29: PROPELA P2-DCM | B29: =P!D28 -> 473100 | C29: =P!E28 -> 5.2965922 | E29: PROPELA P2-KDM | F29: =P!D138 -> 763100 | G29: =P!E138 -> 26.386592 | I29: PROPELA P2-KIC | J29: =P!D176 -> 880000 | K29: =P!E176 -> 32
A30: PLACAS | B30: =INSUMOS!B537 -> 50000 | E30: PLACAS | F30: =INSUMOS!B537 -> 50000 | I30: PLACAS | J30: =INSUMOS!B537 -> 50000
A31: TORNILLOS AG PEQUEÑO | B31: =INSUMOS!B534 -> 50000 | C31: =INSUMOS!E534 -> 3 | E31: TORNILLOS AG MEDIANO | F31: =INSUMOS!B535 -> 80000 | G31: =INSUMOS!E535 -> 5 | I31: TORNILLOS AG MEDIANO | J31: =INSUMOS!B535 -> 80000 | K31: =INSUMOS!E535 -> 5
A32: TOTAL | B32: =SUM(B25:B31) -> 2131660 | C32: =SUM(C25:C31) -> 33.451431 | E32: TOTAL MATERIALES | F32: =SUM(F25:F31) -> 2512900 | G32: =SUM(G25:G31) -> 82.666432 | I32: TOTAL MATERIALES | J32: =SUM(J25:J31) -> 9335345 | K32: =SUM(K25:K31) -> 209.51242
A34: V2AG-14C086 | E34: V2AJ-21E063
A35: Elemento | B35: Precio | C35: PESO (KG) | E35: Elemento | F35: Precio | G35: PESO (KG)
A36: MR 0.55kW @ 85 RPM – RF37DRS71M4 | B36: =INSUMOS!B437 -> 1430000 | C36: =INSUMOS!E437 -> 36 | E36: MR 1,1kW @ 63RPM SK5721IEC90SK90S4 | F36: =INSUMOS!B526 -> 1400000 | G36: =INSUMOS!E527 -> 29
A37: Pletina 210 * 1/4" | B37: =INSUMOS!B112 -> 96000 | C37: =INSUMOS!E112 -> 2.1982747 | E37: Pletina 210 * 1/4" | F37: =INSUMOS!B112 -> 96000 | G37: =INSUMOS!E112 -> 2.1982747
A38: EJE EJDA145C | B38: =EJXA!D26 -> 152800 | C38: =EJXA!E26 -> 9.0118717 | E38: EJE EJDA210E | F38: =EJXA!D60 -> 400400 | G38: =EJXA!E60 -> 33.412291
A39: ACOPLE AD-025-032 | B39: =AD!D18 -> 232800 | C39: =AD!E18 -> 3.182123 | E39: ACOPLE AD-035-050 | F39: =AD!D25 -> 358200 | G39: =AD!E39 -> 7.1597767
A40: PROPELA P2-HCM | B40: =P!D38 -> 563465 | C40: =P!E38 -> 6.4665922 | E40: PROPELA P2-KEM | F40: =P!D148 -> 859150 | G40: =P!E148 -> 29.369833
A41: PLACAS | B41: =INSUMOS!B537 -> 50000 | E41: PLACAS | F41: =INSUMOS!B537 -> 50000
A42: TORNILLOS AG PEQUEÑO | B42: =INSUMOS!B534 -> 50000 | C42: =INSUMOS!E534 -> 3 | E42: TORNILLOS AG MEDIANO | F42: =INSUMOS!B535 -> 80000 | G42: =INSUMOS!E535 -> 5
A43: TOTAL | B43: =SUM(B36:B42) -> 2575065 | C43: =SUM(C36:C42) -> 59.858862 | E43: TOTAL MATERIALES | F43: =SUM(F36:F42) -> 3243750 | G43: =SUM(G36:G42) -> 106.14018

Sheet V3
A1: V3AB-06B293 | E1: V3AF-13D129 | I1: V3AJ-20F159
A2: Elemento | B2: Precio | C2: PESO (KG) | E2: Elemento | F2: Precio | G2: PESO (KG) | I2: Elemento | J2: Precio | K2: PESO (KG)
A3: MR 0.37kW @ 293 RPM RF07DRS71S4 | B3: =INSUMOS!B424 -> 1155000 | C3: =INSUMOS!E424 -> 9 | E3: MR 0.75kW @ 129 RPM RF27DRS80S4 | F3: =INSUMOS!B432 -> 1492202.8 | G3: =INSUMOS!E432 -> 21 | I3: MR 1,5kW @ 159 RPM SK12-90L/4 | J3: =INSUMOS!B518 -> 1259874 | K3: =INSUMOS!E518 -> 43
A4: Pletina 210 * 1/4" | B4: =INSUMOS!B112 -> 96000 | C4: =INSUMOS!E112 -> 2.1982747 | E4: Pletina 210 * 1/4" | F4: =INSUMOS!B112 -> 96000 | G4: =INSUMOS!E112 -> 2.1982747 | I4: Pletina 210 * 1/4" | J4: =INSUMOS!B112 -> 96000 | K4: =INSUMOS!E112 -> 2.1982747
A5: EJE EJDA059B | B5: =EJXA!D67 -> 83010 | C5: =EJXA!E67 -> 2.3468157 | E5: EJE EJDA135C | F5: =EJXA!D100 -> 146400 | G5: =EJXA!E100 -> 8.3903633 | I5: EJE EJDA206D | J5: =EJXA!D121 -> 256220 | K5: =EJXA!E121 -> 18.436425
A6: ACOPLE AD-020-025 | B6: =AD!D5 -> 197400 | C6: =AD!E5 -> 1.7899442 | E6: ACOPLE AD-020-032 | F6: =AD!D12 -> 232800 | G6: =AD!E12 -> 3.182123 | I6: ACOPLE AD-025-038 | J6: =AD!D32 -> 232800 | K6: =AD!E32 -> 3.182123
A7: PROPELA P3-BBM | B7: =P!D187 -> 436250 | C7: =P!E187 -> 2.2424581 | E7: PROPELA P3-GCM | F7: =P!D217 -> 573100 | G7: =P!E217 -> 7.1865922 | I7: PROPELA P3-KDC | J7: =P!D246 -> 790000 | K7: =P!E246 -> 14.3
A8: PLACAS | B8: =INSUMOS!B537 -> 50000 | E8: PLACAS | F8: =INSUMOS!B537 -> 50000 | I8: PLACAS | J8: =INSUMOS!B537 -> 50000
A9: TORNILLOS AG PEQUEÑO | B9: =INSUMOS!B534 -> 50000 | C9: =INSUMOS!E534 -> 3 | E9: TORNILLOS AG PEQUEÑO | F9: =INSUMOS!B534 -> 50000 | G9: =INSUMOS!E534 -> 3 | I9: TORNILLOS AG MEDIANO | J9: =INSUMOS!B535 -> 80000 | K9: =INSUMOS!E535 -> 5
A10: TOTAL MATERIALES | B10: =SUM(B3:B9) -> 2067660 | C10: =SUM(C3:C9) -> 20.577493 | E10: TOTAL MATERIALES | F10: =SUM(F3:F9) -> 2640502.8 | G10: =SUM(G3:G9) -> 44.957353 | I10: TOTAL MATERIALES | J10: =SUM(J3:J9) -> 2764894 | K10: =SUM(K3:K9) -> 86.116823
A12: V3AC-09A189 | E12: V3AH-16G118 | I12: V3AK-26G118
A13: Elemento | B13: Precio | C13: PESO (KG) | E13: Elemento | F13: Precio | G13: PESO (KG) | I13: Elemento | J13: Precio | K13: PESO (KG)
A14: MR 0.25kW @ 189 RPM RF07DRS71S4 | B14: =INSUMOS!B424 -> 1155000 | C14: =INSUMOS!E424 -> 9 | E14: MR 2,2kW @ 118 RPM RF47DRS90L4 | F14: =INSUMOS!B448 -> 1893000 | G14: =INSUMOS!E445 -> 43 | I14: MR 2,2kW @ 118 RPM RF47DRS90L4 | J14: =INSUMOS!B448 -> 1893000 | K14: =INSUMOS!E446 -> 43
A15: Pletina 210 * 1/4" | B15: =INSUMOS!B112 -> 96000 | C15: =INSUMOS!E112 -> 2.1982747 | E15: Pletina 210 * 1/4" | F15: =INSUMOS!B112 -> 96000 | G15: =INSUMOS!E112 -> 2.1982747 | I15: Pletina 210 * 1/4" | J15: =INSUMOS!B112 -> 96000 | K15: =INSUMOS!E112 -> 2.1982747
A16: EJE EJDA086B | B16: =EJXA!D74 -> 93540 | C16: =EJXA!E74 -> 3.4207822 | E16: EJE EJDA162E | F16: =EJXA!D107 -> 326480 | G16: =EJXA!E107 -> 25.775196 | I16: EJE EJDA260E | J16: =EJXA!D140 -> 477400 | K16: =EJXA!E140 -> 41.367599
A17: ACOPLE AD-020-025 | B17: =AD!D5 -> 197400 | C17: =AD!E5 -> 1.7899442 | E17: ACOPLE AD-030-050 | F17: =AD!D46 -> 358200 | G17: =AD!E46 -> 7.1597767 | I17: ACOPLE AD-030-050 | J17: =AD!D46 -> 358200 | K17: =AD!E46 -> 7.1597767
A18: PROPELA P3-CBM | B18: =P!D197 -> 451250 | C18: =P!E197 -> 2.9424581 | E18: PROPELA P3-IEM | F18: =P!D227 -> 759150 | G18: =P!E227 -> 10.869833 | I18: PROPELA P3-LEC | J18: =P!D256 -> 1220000 | K18: =P!E256 -> 26.5
A19: PLACAS | B19: =INSUMOS!B537 -> 50000 | E19: PLACAS | F19: =INSUMOS!B537 -> 50000 | I19: PLACAS | J19: =INSUMOS!B537 -> 50000
A20: TORNILLOS AG PEQUEÑO | B20: =INSUMOS!B534 -> 50000 | C20: =INSUMOS!E534 -> 3 | E20: TORNILLOS AG MEDIANO | F20: =INSUMOS!B535 -> 80000 | G20: =INSUMOS!E535 -> 5 | I20: TORNILLOS AG GRANDE | J20: =INSUMOS!B536 -> 120000 | K20: =INSUMOS!E536 -> 9
A21: TOTAL MATERIALES | B21: =SUM(B14:B20) -> 2093190 | C21: =SUM(C14:C20) -> 22.351459 | E21: TOTAL MATERIALES | F21: =SUM(F14:F20) -> 3562830 | G21: =SUM(G14:G20) -> 94.00308 | I21: TOTAL MATERIALES | J21: =SUM(J14:J20) -> 4214600 | K21: =SUM(K14:K20) -> 129.22565
A23: V3AE-11B120 | E23: V3AI-18F089 | I23: V3AL-26H095
A24: Elemento | B24: Precio | C24: PESO (KG) | E24: Elemento | F24: Precio | G24: PESO (KG) | I24: Elemento | J24: Precio | K24: PESO (KG)
A25: MR 0.37kW @ 120 RPM RF07DRS71S4 | B25: =INSUMOS!B424 -> 1155000 | C25: =INSUMOS!E424 -> 9 | E25: MR 1,5kW @ 89 RPM RF47DRS90M4 | F25: =INSUMOS!B446 -> 1993000 | G25: =INSUMOS!E448 -> 43 | I25: MR 3kW @ 95 RPM RF67DRS100M4 | J25: =INSUMOS!B465 -> 2486000 | K25: =INSUMOS!E465 -> 73
A26: Pletina 210 * 1/4" | B26: =INSUMOS!B112 -> 96000 | C26: =INSUMOS!E112 -> 2.1982747 | E26: Pletina 210 * 1/4" | F26: =INSUMOS!B112 -> 96000 | G26: =INSUMOS!E112 -> 2.1982747 | I26: Pletina 250 * 1/4" | J26: =INSUMOS!B113 -> 100000 | K26: =INSUMOS!E113 -> 3.1154687
A27: EJE EJDA108B | B27: =EJXA!D93 -> 102120 | C27: =EJXA!E93 -> 4.295866 | E27: EJE EJDA184E | F27: =EJXA!D114 -> 360360 | G27: =EJXA!E114 -> 29.275531 | I27: EJE EJDA264E | J27: =EJXA!D147 -> 483560 | K27: =EJXA!E147 -> 42.004023
A28: ACOPLE AD-020-025 | B28: =AD!D5 -> 197400 | C28: =AD!E5 -> 1.7899442 | E28: ACOPLE AD-030-050 | F28: =AD!D46 -> 358200 | G28: =AD!E46 -> 7.1597767 | I28: ACOPLE AD-035-050 | J28: =AD!D39 -> 358200 | K28: =AD!E39 -> 7.1597767
A29: PROPELA P3-EBM | B29: =P!D207 -> 476250 | C29: =P!E207 -> 4.5424581 | E29: PROPELA P3-JEC | F29: =P!D236 -> 745000 | G29: =P!E236 -> 13.8 | I29: PROPELA P3-MEC | J29: =P!D266 -> 2070000 | K29: =P!E266 -> 32.5
A30: PLACAS | B30: =INSUMOS!B537 -> 50000 | E30: PLACAS | F30: =INSUMOS!B537 -> 50000 | I30: PLACAS | J30: =INSUMOS!B537 -> 50000
A31: TORNILLOS AG PEQUEÑO | B31: =INSUMOS!B534 -> 50000 | C31: =INSUMOS!E534 -> 3 | E31: TORNILLOS AG MEDIANO | F31: =INSUMOS!B535 -> 80000 | G31: =INSUMOS!E535 -> 5 | I31: TORNILLOS AG GRANDE | J31: =INSUMOS!B536 -> 120000 | K31: =INSUMOS!E536 -> 9
A32: TOTAL MATERIALES | B32: =SUM(B25:B31) -> 2126770 | C32: =SUM(C25:C31) -> 24.826543 | E32: TOTAL MATERIALES | F32: =SUM(F25:F31) -> 3682560 | G32: =SUM(G25:G31) -> 100.43358 | I32: TOTAL MATERIALES | J32: =SUM(J25:J31) -> 5667760 | K32: =SUM(K25:K31) -> 166.77927
A34: V3AC-06A163
A35: Elemento | B35: Precio | C35: PESO (KG)
A36: MR 0.25kW @ 163 RPM SK072 | B36: =INSUMOS!B524 -> 850000 | C36: =INSUMOS!E524 -> 9
A37: Pletina 170 * 1/4" | B37: =INSUMOS!B111 -> 90000 | C37: =INSUMOS!E111 -> 1.4405927
A38: EJE EJDA065B | B38: =EJXA!D5 -> 85350 | C38: =EJXA!E5 -> 2.5854749
A39: ACOPLE AD-020-025 | B39: =AD!D5 -> 197400 | C39: =AD!E5 -> 1.7899442
A40: PROPELA P3-CBM | B40: =P!D197 -> 451250 | C40: =P!E218 -> 0
A41: PLACAS | B41: =INSUMOS!B537 -> 50000
A42: TORNILLOS AG PEQUEÑO | B42: =INSUMOS!B534 -> 50000 | C42: =INSUMOS!E545 -> 0
A43: TOTAL MATERIALES | B43: =SUM(B36:B42) -> 1774000 | C43: =SUM(C36:C42) -> 14.816012

Sheet V4
A1: V4AE-09B107 | E1: V4AK-27G053
A2: Elemento | B2: Precio | C2: PESO (KG) | E2: Elemento | F2: Precio | G2: PESO (KG)
A3: MR 0.37 kW @ 107 RPM RF17DRS71S4 | B3: =INSUMOS!B426 -> 1200000 | C3: =INSUMOS!E426 -> 16 | E3: MR 2,2 kW @ 53 RPM RF77DRS90L4 | F3: =INSUMOS!B474 -> 3065000 | G3: =INSUMOS!E474 -> 115
A4: Pletina 210 * 1/4" | B4: =INSUMOS!B112 -> 96000 | C4: =INSUMOS!E112 -> 2.1982747 | E4: Pletina 300 * 1/4" | F4: =INSUMOS!B116 -> 110000 | G4: =INSUMOS!E116 -> 4.486275
A5: EJE EJDA090B | B5: =EJXA!D12 -> 95100 | C5: =EJXA!E12 -> 3.5798883 | E5: EJE EJBC270G | F5: =EJXC!D20 -> 1711923 | G5: =EJXC!E20 -> 35.44
A6: ACOPLE AD-020-025 | B6: =AD!D5 -> 197400 | C6: =AD!E5 -> 1.7899442 | E6: ACOPLE AB-3-40 | F6: =AB!D27 -> 546265 | G6: =AB!E27 -> 9.0468716
A7: PROPELA P4-EBM | B7: =P!D306 -> 526250 | C7: =P!E306 -> 5.6424581 | E7: PROPELA P4-LGC | F7: =P!D366 -> 1486000 | G7: =P!C366 -> TOTAL
A8: PLACAS | B8: =INSUMOS!B537 -> 50000 | E8: PLACAS | F8: =INSUMOS!B537 -> 50000
A9: TORNILLOS AG PEQUEÑO | B9: =INSUMOS!B534 -> 50000 | C9: =INSUMOS!E534 -> 3 | E9: TORNILLOS AG MEDIANO | F9: =INSUMOS!B535 -> 80000 | G9: =INSUMOS!E535 -> 5
A10: TOTAL MATERIALES | B10: =SUM(B3:B9) -> 2214750 | C10: =SUM(C3:C9) -> 32.210565 | E10: TOTAL MATERIALES | F10: =SUM(F3:F9) -> 7049188 | G10: =SUM(G3:G9) -> 168.97315
A12: V4AH-12E068 | E12: V4AL-27H043
A13: Elemento | B13: Precio | C13: PESO (KG) | E13: Elemento | F13: Precio | G13: PESO (KG)
A14: MR 1,1 kW @ 68 RPM SK1 SMI 63 | B14: =INSUMOS!B522 -> 1400000 | C14: =INSUMOS!E445 -> 43 | E14: MR 3 kW @ 43 RPM RF87DRS100M4 | F14: =INSUMOS!B482 -> 4102000 | G14: =INSUMOS!E482 -> 145
A15: Pletina 210 * 1/4" | B15: =INSUMOS!B112 -> 96000 | C15: =INSUMOS!E112 -> 2.1982747 | E15: Pletina 350 * 1/4" | F15: =INSUMOS!B117 -> 115000 | G15: =INSUMOS!E117 -> 6.1063187
A16: EJE EJDA125E | B16: =EJXA!D186 -> 269500 | C16: =EJXA!E154 -> 23.865922 | E16: EJE EJBC270I | F16: =EJXC!D13 -> 2618025 | G16: =EJXC!E13 -> 50.443
A17: ACOPLE AD-030-050 | B17: =AD!D46 -> 358200 | C17: =AD!E46 -> 7.1597767 | E17: ACOPLE AB-4-50 | F17: =AB!D13 -> 647320 | G17: =AB!E13 -> 15.909944
A18: PROPELA P4-IEC | B18: =P!D315 -> 690000 | C18: =P!E315 -> 12.7 | E18: PROPELA P4-MIC | F18: =P!D335 -> 2216000 | G18: =P!E335 -> 89.2
A19: PLACAS | B19: =INSUMOS!B537 -> 50000 | E19: PLACAS | F19: =INSUMOS!B537 -> 50000
A20: TORNILLOS AG PEQUEÑO | B20: =INSUMOS!B534 -> 50000 | C20: =INSUMOS!E534 -> 3 | E20: TORNILLOS AG GRANDE | F20: =INSUMOS!B536 -> 120000 | G20: =INSUMOS!E536 -> 9
A21: TOTAL MATERIALES | B21: =SUM(B14:B20) -> 2913700 | C21: =SUM(C14:C20) -> 91.923974 | E21: TOTAL MATERIALES | F21: =SUM(F14:F20) -> 9868345 | G21: =SUM(G14:G20) -> 315.65926
A23: V4AJ-21E065 | E23: V4AV-27H033
A24: Elemento | B24: Precio | C24: PESO (KG) | E24: Elemento | F24: Precio | G24: PESO (KG)
A25: MR 1,1 kW @ 65 RPM RF47DRS80M4 | B25: =INSUMOS!B445 -> 1882100 | C25: =INSUMOS!E445 -> 43 | E25: MR 3 kW @ 33 RPM RF87DRS100M4 | F25: =INSUMOS!B482 -> 4102000 | G25: =INSUMOS!E482 -> 145
A26: Pletina 210 * 1/4" | B26: =INSUMOS!B112 -> 96000 | C26: =INSUMOS!E112 -> 2.1982747 | E26: Pletina 350 * 1/4" | F26: =INSUMOS!B117 -> 115000 | G26: =INSUMOS!E117 -> 6.1063187
A27: EJE EJDA216E | B27: =EJXA!D161 -> 409640 | C27: =EJXA!E161 -> 34.366928 | E27: EJE EJBC270I | F27: =EJXC!D13 -> 2618025 | G27: =EJXC!E13 -> 50.443
A28: ACOPLE AD-030-050 | B28: =AD!D46 -> 358200 | C28: =AD!E46 -> 7.1597767 | E28: ACOPLE AB-4-50 | F28: =AB!D13 -> 647320 | G28: =AB!E13 -> 15.909944
A29: PROPELA P4-KEC | B29: =P!D325 -> 820000 | C29: =P!E325 -> 39.4 | E29: PROPELA P4-RIC | F29: =P!D346 -> 2670000 | G29: =P!E346 -> 108.4
A30: PLACAS | B30: =INSUMOS!B537 -> 50000 | E30: PLACAS | F30: =INSUMOS!B537 -> 50000
A31: TORNILLOS AG PEQUEÑO | B31: =INSUMOS!B534 -> 50000 | C31: =INSUMOS!E534 -> 3 | E31: TORNILLOS AG GRANDE | F31: =INSUMOS!B536 -> 120000 | G31: =INSUMOS!E536 -> 9
A32: TOTAL MATERIALES | B32: =SUM(B25:B31) -> 3665940 | C32: =SUM(C25:C31) -> 129.12498 | E32: TOTAL MATERIALES | F32: =SUM(F25:F31) -> 10322345 | G32: =SUM(G25:G31) -> 334.85926

Sheet OTROS AG
B2: VR23B-016/020
B3: Elemento | C3: Precio | D3: PESO (KG)
B4: MR 0,37 kW @ 325 RPM SF37DRS71S4 | C4: =INSUMOS!B531 -> 950000 | D4: =INSUMOS!E531 -> 25
B5: Pletina 210 * 1/4" | C5: =INSUMOS!B112 -> 96000 | D5: =INSUMOS!E112 -> 2.1982747
B6: EJE EJDA125B | C6: =EJXA!D174 -> 108750 | D6: =EJXA!E174 -> 4.9720671
B7: ACOPLE AD-020-025 | C7: =AD!D5 -> 197400 | D7: =AD!E5 -> 1.7899442
B8: PROPELA P2-ABM | C8: =P!B58 -> 0 | D8: =P!E58 -> 2.2424581
B9: PROPELA P3-BBM | C9: =P!B187 -> 0 | D9: =P!E187 -> 2.2424581
B10: PLACAS | C10: =INSUMOS!B537 -> 50000
B11: TORNILLOS AG PEQUEÑO | C11: =INSUMOS!B534 -> 50000 | D11: =INSUMOS!I535 -> 0
B12: TOTAL MATERIALES | C12: =SUM(C4:C11) -> 1452150 | D12: =SUM(D4:D11) -> 38.445202
B15: V3AC2AB06A163
B16: Elemento | C16: Precio | D16: PESO (KG)
B17: MR 0.25kW @ 163 RPM SK072 | C17: =INSUMOS!B524 -> 850000 | D17: =INSUMOS!E424 -> 9
B18: Pletina 170 * 1/4" | C18: =INSUMOS!B111 -> 90000 | D18: =INSUMOS!E111 -> 1.4405927
B19: EJE EJDA065B | C19: =EJXA!D5 -> 85350 | D19: =EJXA!E5 -> 2.5854749
B20: ACOPLE AD-020-025 | C20: =AD!D5 -> 197400 | D20: =EJXA!E5 -> 2.5854749
B21: PROPELA P2-BBM | C21: =P!D8 -> 391250 | D21: =P!E8 -> 2.3124581
B22: PROPELA P3-CBM | C22: =P!D197 -> 451250 | D22: =P!E197 -> 2.9424581
B23: PLACAS | C23: =INSUMOS!B537 -> 50000
B24: TORNILLOS AG PEQUEÑO | C24: =INSUMOS!B534 -> 50000 | D24: =INSUMOS!E534 -> 3
B25: TOTAL MATERIALES | C25: =SUM(C17:C24) -> 2165250 | D25: =SUM(D17:D24) -> 23.866459
B28: V3AC-06A163
B29: Elemento | C29: Precio | D29: PESO (KG)
B30: MR 0.25kW @ 163 RPM SK072 | C30: =INSUMOS!B524 -> 850000 | D30: =INSUMOS!E524 -> 9
B31: Pletina 170 * 1/4" | C31: =INSUMOS!B111 -> 90000 | D31: =INSUMOS!E111 -> 1.4405927
B32: EJE EJDA065B | C32: =EJXA!D5 -> 85350 | D32: =EJXA!E5 -> 2.5854749
B33: ACOPLE AD-020-025 | C33: =AD!D5 -> 197400 | D33: =EJXA!E5 -> 2.5854749
B34: PROPELA P3-CBM | C34: =P!D197 -> 451250 | D34: =P!E197 -> 2.9424581
B35: PLACAS | C35: =INSUMOS!B537 -> 50000
B36: TORNILLOS AG PEQUEÑO | C36: =INSUMOS!B534 -> 50000 | D36: =INSUMOS!E534 -> 3
B37: TOTAL MATERIALES | C37: =SUM(C30:C36) -> 1774000 | D37: =SUM(D30:D36) -> 21.554001
B39: V6AE-09A085
B40: Elemento | C40: Precio | D40: PESO (KG)
B41: MR 0.25kW @ 85 RPM SK1SMI31 | C41: =INSUMOS!B520 -> 800000 | D41: =INSUMOS!E520 -> 12
B42: Pletina 170 * 1/4" | C42: =INSUMOS!B111 -> 90000 | D42: =INSUMOS!E111 -> 1.4405927
B43: EJE EJDA090B | C43: =EJXA!D12 -> 95100 | D43: =EJXA!E12 -> 3.5798883
B44: ACOPLE AD-020-025 | C44: =AD!D5 -> 197400 | D44: =AD!E5 -> 1.7899442
B45: PROPELA P0-EBM | C45: =P!D434 -> 576250 | D45: =P!E208 -> 0
B46: PLACAS | C46: =INSUMOS!B537 -> 50000
B47: TORNILLOS AG PEQUEÑO | C47: =INSUMOS!B534 -> 50000 | D47: =INSUMOS!E534 -> 3
B48: TOTAL MATERIALES | C48: =SUM(C41:C47) -> 1858750 | D48: =SUM(D41:D47) -> 21.810425
B50: V4AE-09A085
B51: Elemento | C51: Precio | D51: PESO (KG)
B52: MR 0.25kW @ 85 RPM SK1SMI31 | C52: =INSUMOS!B520 -> 800000 | D52: =INSUMOS!E520 -> 12
B53: Pletina 170 * 1/4" | C53: =INSUMOS!B111 -> 90000 | D53: =INSUMOS!E111 -> 1.4405927
B54: EJE EJDA090B | C54: =EJXA!D12 -> 95100 | D54: =EJXA!E12 -> 3.5798883
B55: ACOPLE AD-020-025 | C55: =AD!D5 -> 197400 | D55: =AD!E5 -> 1.7899442
B56: PROPELA P4-EBM | C56: =P!D306 -> 526250 | D56: =P!E306 -> 5.6424581
B57: PLACAS | C57: =INSUMOS!B537 -> 50000
B58: TORNILLOS AG PEQUEÑO | C58: =INSUMOS!B534 -> 50000 | D58: =INSUMOS!E534 -> 3
B59: TOTAL MATERIALES | C59: =SUM(C52:C58) -> 1808750 | D59: =SUM(D52:D58) -> 27.452883

Sheet EJXA
A1: EJDA065B
A2: Elemento | B2: Precio Unit. | C2: Cant. | D2: Parcial | E2: Peso (kg)
A3: Barra 1 " * 650 mm 304SS | B3: =INSUMOS!B2 -> 39000 | C3: 0.65 | D3: =C3*B3 -> 25350 | E3: =C3*INSUMOS!E2 -> 2.5854749
A4: Mecanizado eje macizo 1" | B4: =INSUMOS!B259 -> 60000 | C4: 1 | D4: =C4*B4 -> 60000 | E4: -
C5: TOTAL | D5: =SUM(D3:D4) -> 85350 | E5: =SUM(E3:E4) -> 2.5854749
A8: EJDA090B
A9: Elemento | B9: Precio | E9: Peso (kg)
A10: Barra 1 " * 900 mm 304SS | B10: =INSUMOS!B2 -> 39000 | C10: 0.9 | D10: =C10*B10 -> 35100 | E10: =C10*INSUMOS!E2 -> 3.5798883
A11: Mecanizado eje macizo 1" | B11: =INSUMOS!B259 -> 60000 | C11: 1 | D11: =C11*B11 -> 60000 | E11: -
C12: TOTAL | D12: =SUM(D10:D11) -> 95100 | E12: =SUM(E10:E11) -> 3.5798883
A15: EJDA109C
A16: Elemento | B16: Precio | C16: Cant. | D16: Parcial | E16: Peso (kg)
A17: Barra 1 1/4" * 1090 mm 304SS | B17: =INSUMOS!B3 -> 64000 | C17: 1.09 | D17: =C17*B17 -> 69760 | E17: =C17*INSUMOS!E3 -> 6.7744415
A18: Mecanizado eje macizo 1 1/4" | B18: =INSUMOS!B260 -> 60000 | C18: 1 | D18: =C18*B18 -> 60000 | E18: -
C19: TOTAL | D19: =SUM(D17:D18) -> 129760 | E19: =SUM(E17:E18) -> 6.7744415
A22: EJDA145C
A23: Elemento | B23: Precio | C23: Cant. | D23: Parcial | E23: Peso (kg)
A24: Barra 1 1/4" * 1450 mm 304SS | B24: =INSUMOS!B3 -> 64000 | C24: 1.45 | D24: =C24*B24 -> 92800 | E24: =C24*INSUMOS!E3 -> 9.0118717
A25: Mecanizado eje macizo 1 1/4" | B25: =INSUMOS!B260 -> 60000 | C25: 1 | D25: =C25*B25 -> 60000 | E25: -
C26: TOTAL | D26: =SUM(D24:D25) -> 152800 | E26: =SUM(E24:E25) -> 9.0118717
A29: EJDA160E
A30: Elemento | B30: Precio | C30: Cant. | D30: Parcial | E30: Peso (kg)
A31: Barra 2" * 1600 mm 304SS | B31: =INSUMOS!B5 -> 154000 | C31: 1.6 | D31: =C31*B31 -> 246400 | E31: =C31*INSUMOS!E5 -> 25.456984
A32: Mecanizado eje macizo 1 1/4" | B32: =INSUMOS!B262 -> 77000 | C32: 1 | D32: =C32*B32 -> 77000 | E32: -
C33: TOTAL | D33: =SUM(D31:D32) -> 323400 | E33: =SUM(E31:E32) -> 25.456984
A35: EJDA106DS
A36: Elemento | B36: Precio | C36: Cant. | D36: Parcial | E36: Peso (kg)
A37: Barra 1 1/2 " * 1060 mm 316SS | B37: =INSUMOS!B15 -> 140000 | C37: 1.06 | D37: =C37*B37 -> 148400 | E37: =C37*INSUMOS!E4 -> 9.4867041
A38: Mecanizado eje macizo 1 1/2" | B38: =INSUMOS!B261 -> 77000 | C38: 1 | D38: =C38*B38 -> 77000 | E38: -
C39: TOTAL | D39: =SUM(D37:D38) -> 225400 | E39: =SUM(E37:E38) -> 9.4867041
A42: EJDA180E
A43: Elemento | B43: Precio | C43: Cant. | D43: Parcial | E43: Peso (kg)
A44: Barra 2 " * 1800 mm 304SS | B44: =INSUMOS!B5 -> 154000 | C44: 1.8 | D44: =C44*B44 -> 277200 | E44: =C44*INSUMOS!E5 -> 28.639107
A45: Mecanizado eje macizo 2" | B45: =INSUMOS!B262 -> 77000 | C45: 1 | D45: =C45*B45 -> 77000 | E45: -
C46: TOTAL | D46: =SUM(D44:D45) -> 354200 | E46: =SUM(E44:E45) -> 28.639107
A49: EJDA200D
A50: Elemento | B50: Precio | C50: Cant. | D50: Parcial | E50: Peso (kg)
A51: Barra 1 1/2 " * 2000 mm 304SS | B51: =INSUMOS!B4 -> 87000 | C51: 2 | D51: =C51*B51 -> 174000 | E51: =C51*INSUMOS!E4 -> 17.899442
A52: Mecanizado eje macizo 1 1/2" | B52: =INSUMOS!B261 -> 77000 | C52: 1 | D52: =C52*B52 -> 77000 | E52: -
C53: TOTAL | D53: =SUM(D51:D52) -> 251000 | E53: =SUM(E51:E52) -> 17.899442
A56: EJDA210E
A57: Elemento | B57: Precio | C57: Cant. | D57: Parcial | E57: Peso (kg)
A58: Barra 2 " * 2100 mm 304SS | B58: =INSUMOS!B5 -> 154000 | C58: 2.1 | D58: =C58*B58 -> 323400 | E58: =C58*INSUMOS!E5 -> 33.412291
A59: Mecanizado eje macizo2" | B59: =INSUMOS!B262 -> 77000 | C59: 1 | D59: =C59*B59 -> 77000 | E59: -
C60: TOTAL | D60: =SUM(D58:D59) -> 400400 | E60: =SUM(E58:E59) -> 33.412291
A63: EJDA059B
A64: Elemento | B64: Precio | C64: Cant. | D64: Parcial | E64: Peso (kg)
A65: Barra 1 " * 590 mm 304SS | B65: =INSUMOS!B2 -> 39000 | C65: 0.59 | D65: =C65*B65 -> 23010 | E65: =C65*INSUMOS!E2 -> 2.3468157
A66: Mecanizado eje macizo 1" | B66: =INSUMOS!B259 -> 60000 | C66: 1 | D66: =C66*B66 -> 60000 | E66: -
C67: TOTAL | D67: =SUM(D65:D66) -> 83010 | E67: =SUM(E65:E66) -> 2.3468157
A70: EJDA086B
A71: Elemento | B71: Precio | C71: Cant. | D71: Parcial | E71: Peso (kg)
A72: Barra 1 " * 860 mm 304SS | B72: =INSUMOS!B2 -> 39000 | C72: 0.86 | D72: =C72*B72 -> 33540 | E72: =C72*INSUMOS!E2 -> 3.4207822
A73: Mecanizado eje macizo 1" | B73: =INSUMOS!B259 -> 60000 | C73: 1 | D73: =C73*B73 -> 60000 | E73: -
C74: TOTAL | D74: =SUM(D72:D73) -> 93540 | E74: =SUM(E72:E73) -> 3.4207822
A76: EJDA135DS
A77: Elemento | B77: Precio | C77: Cant. | D77: Parcial | E77: Peso (kg)
A78: Barra 1 1/2 " * 1350 mm 316SS | B78: =INSUMOS!B15 -> 140000 | C78: 1.35 | D78: =C78*B78 -> 189000 | E78: =C78*INSUMOS!E4 -> 12.082123
A79: Mecanizado eje macizo 1 1/2" | B79: =INSUMOS!B261 -> 77000 | C79: 1 | D79: =C79*B79 -> 77000 | E79: -
C80: TOTAL | D80: =SUM(D78:D79) -> 266000 | E80: =SUM(E78:E79) -> 12.082123
A82: EJDA180D
A83: Elemento | B83: Precio | C83: Cant. | D83: Parcial | E83: Peso (kg)
A84: Barra 1 1/2 " * 1800 mm 304SS | B84: =INSUMOS!B4 -> 87000 | C84: 1.8 | D84: =C84*B84 -> 156600 | E84: =C84*INSUMOS!E4 -> 16.109498
A85: Mecanizado eje macizo 1 1/2" | B85: =INSUMOS!B261 -> 77000 | C85: 1 | D85: =C85*B85 -> 77000 | E85: -
C86: TOTAL | D86: =SUM(D84:D85) -> 233600 | E86: =SUM(E84:E85) -> 16.109498
A89: EJDA108B
A90: Elemento | B90: Precio | C90: Cant. | D90: Parcial | E90: Peso (kg)
A91: Barra 1 " * 1080 mm 304SS | B91: =INSUMOS!B2 -> 39000 | C91: 1.08 | D91: =C91*B91 -> 42120 | E91: =C91*INSUMOS!E2 -> 4.295866
A92: Mecanizado eje macizo 1" | B92: =+INSUMOS!B259 -> 60000 | C92: 1 | D92: =C92*B92 -> 60000 | E92: -
C93: TOTAL | D93: =SUM(D91:D92) -> 102120 | E93: =SUM(E91:E92) -> 4.295866
A96: EJDA135C
A97: Elemento | B97: Precio | C97: Cant. | D97: Parcial | E97: Peso (kg)
A98: Barra 1 1/4 " * 1350 mm 304SS | B98: =INSUMOS!B3 -> 64000 | C98: 1.35 | D98: =C98*B98 -> 86400 | E98: =C98*INSUMOS!E3 -> 8.3903633
A99: Mecanizado eje macizo 1 1/4" | B99: =INSUMOS!B260 -> 60000 | C99: 1 | D99: =C99*B99 -> 60000 | E99: -
C100: TOTAL | D100: =SUM(D98:D99) -> 146400 | E100: =SUM(E98:E99) -> 8.3903633
A103: EJDA162E
A104: Elemento | B104: Precio | C104: Cant. | D104: Parcial | E104: Peso (kg)
A105: Barra 2 " * 1620 mm 304SS | B105: =INSUMOS!B5 -> 154000 | C105: 1.62 | D105: =C105*B105 -> 249480 | E105: =C105*INSUMOS!E5 -> 25.775196
A106: Mecanizado eje macizo 2" | B106: =INSUMOS!B262 -> 77000 | C106: 1 | D106: =C106*B106 -> 77000 | E106: -
C107: TOTAL | D107: =SUM(D105:D106) -> 326480 | E107: =SUM(E105:E106) -> 25.775196
A110: EJDA184E
A111: Elemento | B111: Precio | C111: Cant. | D111: Parcial | E111: Peso (kg)
A112: Barra 2 " * 1840 mm 304SS | B112: =INSUMOS!B5 -> 154000 | C112: 1.84 | D112: =C112*B112 -> 283360 | E112: =C112*INSUMOS!E5 -> 29.275531
A113: Mecanizado eje macizo 2" | B113: =INSUMOS!B262 -> 77000 | C113: 1 | D113: =C113*B113 -> 77000 | E113: -
C114: TOTAL | D114: =SUM(D112:D113) -> 360360 | E114: =SUM(E112:E113) -> 29.275531
A117: EJDA206D
A118: Elemento | B118: Precio | C118: Cant. | D118: Parcial | E118: Peso (kg)
A119: Barra 1 1/2 " * 2060 mm 304SS | B119: =INSUMOS!B4 -> 87000 | C119: 2.06 | D119: =C119*B119 -> 179220 | E119: =C119*INSUMOS!E4 -> 18.436425
A120: Mecanizado eje macizo 1 1/2" | B120: =INSUMOS!B261 -> 77000 | C120: 1 | D120: =C120*B120 -> 77000 | E120: -
C121: TOTAL | D121: =SUM(D119:D120) -> 256220 | E121: =SUM(E119:E120) -> 18.436425
A123: EJDA135D
A124: Elemento | B124: Precio | C124: Cant. | D124: Parcial | E124: Peso (kg)
A125: Barra 1 1/2 " * 1350 mm 304SS | B125: =INSUMOS!B4 -> 87000 | C125: 1.35 | D125: =C125*B125 -> 117450 | E125: =C125*INSUMOS!E4 -> 12.082123
A126: Mecanizado eje macizo 1 1/2" | B126: =INSUMOS!B261 -> 77000 | C126: 1 | D126: =C126*B126 -> 77000 | E126: -
C127: TOTAL | D127: =SUM(D125:D126) -> 194450 | E127: =SUM(E125:E126) -> 12.082123
A129: EJDA230D
A130: Elemento | B130: Precio | C130: Cant. | D130: Parcial | E130: Peso (kg)
A131: Barra 1 1/2 " * 2300 mm 304SS | B131: =INSUMOS!B4 -> 87000 | C131: 2.3 | D131: =C131*B131 -> 200100 | E131: =C131*INSUMOS!E4 -> 20.584358
A132: Mecanizado eje macizo 1 1/2" | B132: =INSUMOS!B261 -> 77000 | C132: 1 | D132: =C132*B132 -> 77000 | E132: -
C133: TOTAL | D133: =SUM(D131:D132) -> 277100 | E133: =SUM(E131:E132) -> 20.584358
...

Sheet EJXC
A1: EJBC240G
A2: Elemento | B2: Precio Unit | C2: Cant. | D2: Parcial | E2: Peso (kg)
A3: Brida ciega de 3" 304SS | B3: =INSUMOS!B72 -> 98250 | C3: 1 | D3: =C3*B3 -> 98250 | E3: =INSUMOS!E72 -> 4.93
A4: Tubo de 3" SCH 40 304SS 2400 mm | B4: =INSUMOS!B48 -> 751564 | C4: 0.75 | D4: =C4*B4 -> 563673 | E4: =2.4*INSUMOS!E48 -> 27.12
A5: Maquinado de eje tubular de 3" | B5: =INSUMOS!B278 -> 1050000 | C5: 1 | D5: =C5*B5 -> 1050000 | E5: -
C6: TOTAL | D6: =SUM(D3:D5) -> 1711923 | E6: =SUM(E3:E5) -> 32.05
A8: EJBC270I
A9: Elemento | B9: Precio | C9: Cant. | D9: Parcial | E9: Peso (kg)
A10: Brida ciega de 4" 304SS | B10: =INSUMOS!B73 -> 148500 | C10: 1 | D10: =C10*B10 -> 148500 | E10: =INSUMOS!E73 -> 7
A11: Tubo de 4" SCH 40 304SS 2700 mm | B11: =INSUMOS!B49 -> 1052700 | C11: 0.75 | D11: =C11*B11 -> 789525 | E11: =2.7*INSUMOS!E49 -> 43.443
A12: Maquinado de eje tubular de 4" | B12: =INSUMOS!B279 -> 1680000 | C12: 1 | D12: =C12*B12 -> 1680000 | E12: -
C13: TOTAL | D13: =SUM(D10:D12) -> 2618025 | E13: =SUM(E10:E12) -> 50.443
A15: EJBC270G
A16: Elemento | B16: Precio | C16: Cant. | D16: Parcial | E16: Peso (kg)
A17: Brida ciega de 3" 304SS | B17: =INSUMOS!B72 -> 98250 | C17: 1 | D17: =C17*B17 -> 98250 | E17: =INSUMOS!E72 -> 4.93
A18: Tubo de 3" SCH 40 304SS 2700 mm | B18: =INSUMOS!B48 -> 751564 | C18: 0.75 | D18: =C18*B18 -> 563673 | E18: =2.7*INSUMOS!E48 -> 30.51
A19: Maquinado de eje tubular de 3" | B19: =INSUMOS!B278 -> 1050000 | C19: 1 | D19: =C19*B19 -> 1050000 | E19: -
C20: TOTAL | D20: =SUM(D17:D19) -> 1711923 | E20: =SUM(E17:E19) -> 35.44
A22: EJBC740JR
A23: Elemento | B23: Precio | C23: Cant. | D23: Parcial | E23: Peso (kg)
A24: Brida ciega de 6" A36 | B24: =INSUMOS!B103 -> 62500 | C24: 3 | D24: =C24*B24 -> 187500 | E24: =INSUMOS!E103 -> 11.3
A25: Tubo de 6" SCH 40 A36 7400 mm | B25: =INSUMOS!B65 -> 448340 | C25: 1.5 | D25: =C25*B25 -> 672510 | E25: =7.4*INSUMOS!E65 -> 208.68
A26: Maquinado de eje tubular de 6" | B26: =INSUMOS!B281 -> 2300000 | C26: 1 | D26: =C26*B26 -> 2300000 | E26: -
D27: =SUM(D24:D26) -> 3160010 | E27: =SUM(E24:E26) -> 219.98
A29: EJBC200G
A30: Elemento | B30: Precio | C30: Cant. | D30: Parcial | E30: Peso (kg)
A31: Brida ciega de 3" 304SS | B31: =INSUMOS!B72 -> 98250 | C31: 1 | D31: =C31*B31 -> 98250 | E31: =INSUMOS!E72 -> 4.93
A32: Tubo de 3" SCH 40 304SS 2000 mm | B32: =INSUMOS!B48 -> 751564 | C32: 0.5 | D32: =C32*B32 -> 375782 | E32: =1.8*INSUMOS!E48 -> 20.34
A33: Maquinado de eje tubular de 3" | B33: =INSUMOS!B278 -> 1050000 | C33: 1 | D33: =C33*B33 -> 1050000 | E33: -
D34: =SUM(D31:D33) -> 1524032 | E34: =SUM(E31:E33) -> 25.27
A37: EJBC200F
A38: Elemento | B38: Precio | C38: Cant. | D38: Parcial | E38: Peso (kg)
A39: Brida ciega de 2 1/2" 304SS | B39: =INSUMOS!B79 -> 82000 | C39: 1 | D39: =C39*B39 -> 82000 | E39: =INSUMOS!E79 -> 3.28
A40: Tubo de 2 1/2" SCH 40 304SS 2000 mm | B40: =INSUMOS!B47 -> 638000 | C40: 0.5 | D40: =C40*B40 -> 319000 | E40: =2*INSUMOS!E47 -> 17.26
A41: Maquinado de eje tubular de 2 1/2" | B41: =INSUMOS!B277 -> 600000 | C41: 1 | D41: =C41*B41 -> 600000
D42: =SUM(D39:D41) -> 1001000 | E42: =SUM(E39:E41) -> 20.54
A44: EJBC420I
A45: Elemento | B45: Precio | C45: Cant. | D45: Parcial | E45: Peso (kg)
A46: Brida ciega de 4" 304SS | B46: =INSUMOS!B73 -> 148500 | C46: 1 | D46: =C46*B46 -> 148500 | E46: =INSUMOS!E73 -> 7
A47: Tubo de 4" SCH 40 304SS 4200 mm | B47: =INSUMOS!B49 -> 1052700 | C47: 1 | D47: =C47*B47 -> 1052700 | E47: =INSUMOS!E49*4.2 -> 67.578
A48: Maquinado de eje tubular de 4" | B48: =INSUMOS!B279 -> 1680000 | C48: 1 | D48: =C48*B48 -> 1680000 | E48: -
D49: =SUM(D46:D48) -> 2881200 | E49: =SUM(E46:E48) -> 74.578
A51: EJBC370IS
B52: Precio | C52: Cant. | D52: Parcial | E52: Peso (kg)
A53: Brida ciega de 4" 316SS | B53: =INSUMOS!B91 -> 325600 | C53: 1 | D53: =C53*B53 -> 325600 | E53: =INSUMOS!E91 -> 6.8
A54: Tubo de 4" SCH 40 316SS 3700 mm | B54: =INSUMOS!B60 -> 1752000 | C54: 0.75 | D54: =C54*B54 -> 1314000 | E54: =INSUMOS!E60 -> 16.09
A55: Maquinado de eje tubular de 4" | B55: =INSUMOS!B279 -> 1680000 | C55: 1 | D55: =C55*B55 -> 1680000 | E55: -
D56: =SUM(D53:D55) -> 3319600 | E56: =SUM(E53:E55) -> 22.89
A58: EJBC440KS
B59: Precio | C59: Cant. | D59: Parcial | E59: Peso (kg)
A60: Brida ciega de 8" 316SS | B60: =INSUMOS!B93 -> 480000 | C60: 1 | D60: =C60*B60 -> 480000 | E60: =INSUMOS!E93 -> 15
A61: Tubo de 8" SCH 40 316SS 4400 mm | B61: =INSUMOS!B62 -> 4770500 | C61: 1 | D61: =C61*B61 -> 4770500 | E61: =4.4*INSUMOS!E52 -> 187.44
A62: Maquinado de eje tubular de 8" | B62: =INSUMOS!B282 -> 3500000 | C62: 1 | D62: =C62*B62 -> 3500000 | E62: -
D63: =SUM(D60:D62) -> 8750500 | E63: =SUM(E60:E62) -> 202.44
A65: EJBC180F
A66: Elemento | B66: Precio | C66: Cant. | D66: Parcial | E66: Peso (kg)
A67: Brida ciega de 2 1/2" 304SS | B67: =INSUMOS!B79 -> 82000 | C67: 1 | D67: =C67*B67 -> 82000 | E67: =INSUMOS!E71 -> 3
A68: Tubo de 2 1/2" SCH 40 304SS 1800 mm | B68: =INSUMOS!B47 -> 638000 | C68: 0.75 | D68: =C68*B68 -> 478500 | E68: =1.8*INSUMOS!E47 -> 15.534
A69: Maquinado de eje tubular de 2 1/2" | B69: =INSUMOS!B277 -> 600000 | C69: 1 | D69: =C69*B69 -> 600000
D70: =SUM(D67:D69) -> 1160500 | E70: =SUM(E67:E69) -> 18.534
A72: EJBC410JS
B73: Precio | C73: Cant. | D73: Parcial | E73: Peso (kg)
A74: Brida ciega de 6" 316SS | B74: =INSUMOS!B92 -> 330000 | C74: 1 | D74: =C74*B74 -> 330000 | E74: =INSUMOS!E92 -> 11.3
A75: Tubo de 6" SCH 40 316SS 4100 mm | B75: =INSUMOS!B61 -> 3600000 | C75: 1 | D75: =C75*B75 -> 3600000 | E75: =4.1*INSUMOS!E61 -> 115.62
A76: Maquinado de eje tubular de 6" | B76: =INSUMOS!B281 -> 2300000 | C76: 1 | D76: =C76*B76 -> 2300000 | E76: -
D77: =SUM(D74:D76) -> 6230000 | E77: =SUM(E74:E76) -> 126.92
A79: EJBC580J
B80: Precio | C80: Cant. | D80: Parcial | E80: Peso (kg)
A81: Brida ciega de 6" 304SS | B81: =INSUMOS!B74 -> 212000 | C81: 1 | D81: =C81*B81 -> 212000 | E81: =INSUMOS!E74 -> 11.3
A82: Tubo de 6" SCH 40 304SS 4100 mm | B82: =INSUMOS!B51 -> 2978800 | C82: 1 | D82: =C82*B82 -> 2978800 | E82: =4.1*INSUMOS!E51 -> 115.62
A83: Maquinado de eje tubular de 6" | B83: =INSUMOS!B281 -> 2300000 | C83: 1 | D83: =C83*B83 -> 2300000 | E83: -
D84: =SUM(D81:D83) -> 5490800 | E84: =SUM(E81:E83) -> 126.92
A86: EJBC430IS
A87: Elemento | B87: Precio | C87: Cant. | D87: Parcial | E87: Peso (kg)
A88: Brida ciega de 4" 316SS | B88: =INSUMOS!B91 -> 325600 | C88: 1 | D88: =C88*B88 -> 325600 | E88: =INSUMOS!E91 -> 6.8
A89: Tubo de 4" SCH 40 316SS 4300 mm | B89: =INSUMOS!B60 -> 1752000 | C89: 1 | D89: =C89*B89 -> 1752000 | E89: =4.3*INSUMOS!E60 -> 69.187
A90: Maquinado de eje tubular de 4" | B90: =INSUMOS!B279 -> 1680000 | C90: 1 | D90: =C90*B90 -> 1680000 | E90: -
D91: =SUM(D88:D90) -> 3757600 | E91: =SUM(E88:E90) -> 75.987
A93: EJBC170IS
A94: Elemento | B94: Precio | C94: Cant. | D94: Parcial | E94: Peso (kg)
A95: Brida ciega de 4" 316SS | B95: =INSUMOS!B91 -> 325600 | C95: 1 | D95: =C95*B95 -> 325600 | E95: =INSUMOS!E91 -> 6.8
A96: Tubo de 4" SCH 40 316SS 4300 mm | B96: =INSUMOS!B60 -> 1752000 | C96: 0.75 | D96: =C96*B96 -> 1314000 | E96: =1.7*INSUMOS!E60 -> 27.353
A97: Maquinado de eje tubular de 4" | B97: =INSUMOS!B279 -> 1680000 | C97: 1 | D97: =C97*B97 -> 1680000 | E97: -
D98: =SUM(D95:D97) -> 3319600 | E98: =SUM(E95:E97) -> 34.153
A100: EJBC340IS
A101: Elemento | B101: Precio | C101: Cant. | D101: Parcial | E101: Peso (kg)
A102: Brida ciega de 4" 316SS | B102: =INSUMOS!B91 -> 325600 | C102: 1 | D102: =C102*B102 -> 325600 | E102: =INSUMOS!E91 -> 6.8
A103: Tubo de 4" SCH 40 316SS 3400 mm | B103: =INSUMOS!B60 -> 1752000 | C103: 0.75 | D103: =C103*B103 -> 1314000 | E103: =4.3*INSUMOS!E81 -> 22.79
A104: Maquinado de eje tubular de 4" | B104: =INSUMOS!B279 -> 1680000 | C104: 1 | D104: =C104*B104 -> 1680000 | E104: -
D105: =SUM(D102:D104) -> 3319600 | E105: =SUM(E102:E104) -> 29.59
A107: EJBC370F
A108: Elemento | B108: Precio | C108: Cant. | D108: Parcial | E108: Peso (kg)
A109: Brida ciega de 2 1/2" 304SS | B109: =INSUMOS!B71 -> 80000 | C109: 1 | D109: =C109*B109 -> 80000 | E109: =INSUMOS!E71 -> 3
A110: Tubo de 2 1/2" SCH 40 304SS 3700 mm | B110: =INSUMOS!B47 -> 638000 | C110: 0.85 | D110: =C110*B110 -> 542300 | E110: =3.7*INSUMOS!E47 -> 31.931
A111: Maquinado de eje tubular de 2 1/2" | B111: =INSUMOS!B277 -> 600000 | C111: 1 | D111: =C111*B111 -> 600000
D112: =SUM(D109:D111) -> 1222300 | E112: =SUM(E109:E111) -> 34.931
A114: EJBC380G
A115: Elemento | B115: Precio | C115: Cant. | D115: Parcial | E115: Peso (kg)
A116: Brida ciega de 3" 304SS | B116: =INSUMOS!B72 -> 98250 | C116: 1 | D116: =C116*B116 -> 98250 | E116: =INSUMOS!E72 -> 4.93
A117: Tubo de 3" SCH 40 304SS 3800 mm | B117: =INSUMOS!B48 -> 751564 | C117: 0.85 | D117: =C117*B117 -> 638829.4 | E117: =3.8*INSUMOS!E48 -> 42.94
...

Sheet AB
A1: AB-4-60
A2: Elemento | B2: Precio | C2: Cant. | D2: Parcial | E2: Peso (kg)
A3: Brida ciega de 4" 304SS | B3: =INSUMOS!B73 -> 148500 | C3: 1 | D3: =C3*B3 -> 148500 | E3: =INSUMOS!E73 -> 7
A4: Barra 4 " * 160 mm 304SS | B4: =INSUMOS!B8 -> 563000 | C4: 0.16 | D4: =C4*B4 -> 90080 | E4: =0.16*INSUMOS!E8 -> 10.182793
A5: Mecanizado acople bridado 4" | B5: =INSUMOS!B271 -> 420000 | C5: 1 | D5: =C5*B5 -> 420000 | E5: -
C6: TOTAL | D6: =SUM(D3:D5) -> 658580 | E6: =SUM(E3:E5) -> 17.182793
A8: AB-4-50
A9: Elemento | B9: Precio | C9: Cant. | D9: Parcial | E9: Peso (kg)
A10: Brida ciega de 4" 304SS | B10: =INSUMOS!B73 -> 148500 | C10: 1 | D10: =C10*B10 -> 148500 | E10: =INSUMOS!E73 -> 7
A11: Barra 4 " * 140 mm 304SS | B11: =INSUMOS!B8 -> 563000 | C11: 0.14 | D11: =C11*B11 -> 78820 | E11: =0.14*INSUMOS!E8 -> 8.9099443
A12: Mecanizado acople bridado 4" | B12: =INSUMOS!B271 -> 420000 | C12: 1 | D12: =C12*B12 -> 420000 | E12: -
C13: TOTAL | D13: =SUM(D10:D12) -> 647320 | E13: =SUM(E10:E12) -> 15.909944
A15: AB-3-50
A16: Elemento | B16: Precio | C16: Cant. | D16: Parcial | E16: Peso (kg)
A17: Brida ciega de 3" 304SS | B17: =INSUMOS!B72 -> 98250 | C17: 1 | D17: =C17*B17 -> 98250 | E17: =INSUMOS!E72 -> 4.93
A18: Barra 3 " * 135 mm 304SS | B18: =INSUMOS!B7 -> 461000 | C18: 0.135 | D18: =C18*B18 -> 62235 | E18: =0.135*INSUMOS!E7 -> 4.8328493
A19: Mecanizado acople bridado 3" | B19: =INSUMOS!B270 -> 395000 | C19: 1 | D19: =C19*B19 -> 395000 | E19: -
C20: TOTAL | D20: =SUM(D17:D19) -> 555485 | E20: =SUM(E17:E19) -> 9.7628493
A22: AB-3-40
A23: Elemento | B23: Precio | C23: Cant. | D23: Parcial | E23: Peso (kg)
A24: Brida ciega de 3" 304SS | B24: =INSUMOS!B72 -> 98250 | C24: 1 | D24: =C24*B24 -> 98250 | E24: =INSUMOS!E72 -> 4.93
A25: Barra 3 " * 115 mm 304SS | B25: =INSUMOS!B7 -> 461000 | C25: 0.115 | D25: =C25*B25 -> 53015 | E25: =0.115*INSUMOS!E7 -> 4.1168716
A26: Mecanizado acople bridado 3" | B26: =INSUMOS!B270 -> 395000 | C26: 1 | D26: =C26*B26 -> 395000 | E26: -
C27: TOTAL | D27: =SUM(D24:D26) -> 546265 | E27: =SUM(E24:E26) -> 9.0468716
A29: AB-6-60-R
A30: Elemento | B30: Precio | C30: Cant. | D30: Parcial | E30: Peso (kg)
A31: Brida ciega de 6" A36 | B31: =INSUMOS!B103 -> 62500 | C31: 1 | D31: =C31*B31 -> 62500 | E31: =INSUMOS!E103 -> 11.3
A32: Barra 6 " * 170 mm A36 | B32: =INSUMOS!B9 -> 1267000 | C32: 0.17 | D32: =C32*B32 -> 215390 | E32: =INSUMOS!E30*0.17 -> 24.343241
A33: Mecanizado acople bridado 6" | B33: =INSUMOS!B272 -> 1305000 | C33: 1 | D33: =C33*B33 -> 1305000
C34: TOTAL | D34: =SUM(D31:D33) -> 1582890 | E34: =SUM(E31:E33) -> 35.643241
A36: AB-3-35
A37: Elemento | B37: Precio | C37: Cant. | D37: Parcial | E37: Peso (kg)
A38: Brida ciega de 3" 304SS | B38: =INSUMOS!B80 -> 78000 | C38: 1 | D38: =C38*B38 -> 78000 | E38: =INSUMOS!E72 -> 4.93
A39: Barra 3 " * 115 mm 304SS | B39: =INSUMOS!B7 -> 461000 | C39: 0.17 | D39: =C39*B39 -> 78370 | E39: =0.12*INSUMOS!E7 -> 4.295866
A40: Mecanizado acople bridado 3" | B40: =INSUMOS!B270 -> 395000 | C40: 1 | D40: =C40*B40 -> 395000 | E40: -
C41: TOTAL | D41: =SUM(D38:D40) -> 551370 | E41: =SUM(E38:E40) -> 9.225866
A43: AB-2.5-35
A44: Elemento | B44: Precio | C44: Cant. | D44: Parcial | E44: Peso (kg)
A45: Brida ciega de 2,5" 304SS | B45: =INSUMOS!B71 -> 80000 | C45: 1 | D45: =C45*B45 -> 80000 | E45: =INSUMOS!E79 -> 3.28
A46: Barra 3 " * 115 mm 304SS | B46: =INSUMOS!B7 -> 461000 | C46: 0.17 | D46: =C46*B46 -> 78370 | E46: =0.11*INSUMOS!E7 -> 3.9378772
A47: Mecanizado acople bridado 2.5" | B47: =INSUMOS!B269 -> 300000 | C47: 1 | D47: =C47*B47 -> 300000
C48: TOTAL | D48: =SUM(D45:D47) -> 458370 | E48: =SUM(E45:E47) -> 7.2178772
A50: AB-4-50-S
A51: Elemento | B51: Precio | C51: Cant. | D51: Parcial | E51: Peso (kg)
A52: Brida ciega de 4" 316SS | B52: =INSUMOS!B91 -> 325600 | C52: 1 | D52: =C52*B52 -> 325600 | E52: =INSUMOS!E60 -> 16.09
A53: Barra 4 " * 140 mm 316SS | B53: =INSUMOS!B21 -> 720000 | C53: 0.14 | D53: =C53*B53 -> 100800 | E53: =0.16*INSUMOS!E21 -> 10.182793
A54: Mecanizado acople bridado 4" | B54: =INSUMOS!B271 -> 420000 | C54: 1 | D54: =C54*B54 -> 420000 | E54: -
C55: TOTAL | D55: =SUM(D52:D54) -> 846400 | E55: =SUM(E52:E54) -> 26.272793
A57: AB-8-90-S
A58: Elemento | B58: Precio | C58: Cant. | D58: Parcial | E58: Peso (kg)
A59: Brida ciega de 8" 316SS | B59: =INSUMOS!B93 -> 480000 | C59: 1 | D59: =C59*B59 -> 480000 | E59: =INSUMOS!E93 -> 15
A60: Barra 8 " * 250 mm 316SS | B60: =INSUMOS!B23 -> 3594500 | C60: 0.25 | D60: =C60*B60 -> 898625 | E60: =0.25*INSUMOS!E23 -> 63.642459
A61: Mecanizado acople bridado 8" | B61: =INSUMOS!B273 -> 1600000 | C61: 1 | D61: =C61*B61 -> 1600000 | E61: -
C62: TOTAL | D62: =SUM(D59:D61) -> 2978625 | E62: =SUM(E59:E61) -> 78.642459
A64: AB-2.5-40
A65: Elemento | B65: Precio | C65: Cant. | D65: Parcial | E65: Peso (kg)
A66: Brida ciega de 2,5" 304SS | B66: =INSUMOS!B71 -> 80000 | C66: 1 | D66: =C66*B66 -> 80000 | E66: =INSUMOS!E71 -> 3
A67: Barra 3 " * 110 mm 304SS | B67: =INSUMOS!B7 -> 461000 | C67: 0.11 | D67: =C67*B67 -> 50710 | E67: =C67*INSUMOS!E7 -> 3.9378772
A68: Mecanizado acople bridado 2.5" | B68: =INSUMOS!B269 -> 300000 | C68: 1 | D68: =C68*B68 -> 300000
C69: TOTAL | D69: =SUM(D66:D68) -> 430710 | E69: =SUM(E66:E68) -> 6.9378772
A71: AB-6-60-S
A72: Elemento | B72: Precio | C72: Cant. | D72: Parcial | E72: Peso (kg)
A73: Brida ciega de 6" 316SS | B73: =INSUMOS!B92 -> 330000 | C73: 1 | D73: =C73*B73 -> 330000 | E73: =INSUMOS!E92 -> 11.3
A74: Barra 6 " * 220 mm 316SS | B74: =INSUMOS!B22 -> 1944000 | C74: 0.22 | D74: =C74*B74 -> 427680 | E74: =0.22*INSUMOS!E9 -> 31.503017
A75: Mecanizado acople bridado 6" | B75: =INSUMOS!B272 -> 1305000 | C75: 1 | D75: =C75*B75 -> 1305000 | E75: -
C76: TOTAL | D76: =SUM(D73:D75) -> 2062680 | E76: =SUM(E73:E75) -> 42.803017
A78: AB-6-60
A79: Elemento | B79: Precio | C79: Cant. | D79: Parcial | E79: Peso (kg)
A80: Brida ciega de 6" 304SS | B80: =INSUMOS!B74 -> 212000 | C80: 1 | D80: =C80*B80 -> 212000 | E80: =INSUMOS!E103 -> 11.3
A81: Barra 6 " * 220 mm 304SS | B81: =INSUMOS!B9 -> 1267000 | C81: 0.22 | D81: =C81*B81 -> 278740 | E81: =0.22*INSUMOS!E22 -> 31.504
A82: Mecanizado acople bridado 6" | B82: =INSUMOS!B272 -> 1305000 | C82: 1 | D82: =C82*B82 -> 1305000 | E82: -
C83: TOTAL | D83: =SUM(D80:D82) -> 1795740 | E83: =SUM(E80:E82) -> 42.804
A85: AB-4-40-S
A86: Elemento | B86: Precio | C86: Cant. | D86: Parcial | E86: Peso (kg)
A87: Brida ciega de 4" 316SS | B87: =INSUMOS!B91 -> 325600 | C87: 1 | D87: =C87*B87 -> 325600 | E87: =INSUMOS!E91 -> 6.8
A88: Barra 4 " * 120 mm 316SS | B88: =INSUMOS!B21 -> 720000 | C88: 0.12 | D88: =C88*B88 -> 86400 | E88: =C88*INSUMOS!E21 -> 7.6370951
A89: Mecanizado acople bridado 4" | B89: =INSUMOS!B271 -> 420000 | C89: 1 | D89: =C89*B89 -> 420000 | E89: -
C90: TOTAL | D90: =SUM(D87:D89) -> 832000 | E90: =SUM(E87:E89) -> 14.437095
A92: AB-2-30
A93: Elemento | B93: Precio | C93: Cant. | D93: Parcial | E93: Peso (kg)
A94: Brida ciega de 2" 304SS | B94: =INSUMOS!B78 -> 75000 | C94: 1 | D94: =C94*B94 -> 75000 | E94: =INSUMOS!E78 -> 3
A95: Barra 2 " * 92 mm 304SS | B95: =INSUMOS!B5 -> 154000 | C95: 0.1 | D95: =C95*B95 -> 15400 | E95: =C95*INSUMOS!E16 -> 1.5910615
A96: Mecanizado acople bridado 2" | B96: =INSUMOS!B268 -> 250000 | C96: 1 | D96: =C96*B96 -> 250000
C97: TOTAL | D97: =SUM(D94:D96) -> 340400 | E97: =SUM(E94:E96) -> 4.5910615
A99: AB-6-50-S
A100: Elemento | B100: Precio | C100: Cant. | D100: Parcial | E100: Peso (kg)
A101: Brida ciega de 6" 316SS | B101: =INSUMOS!B92 -> 330000 | C101: 1 | D101: =C101*B101 -> 330000 | E101: =INSUMOS!E92 -> 11.3
A102: Barra 6 " * 160 mm 316SS | B102: =INSUMOS!B22 -> 1944000 | C102: 0.22 | D102: =C102*B102 -> 427680 | E102: =C102*INSUMOS!E22 -> 31.504
A103: Mecanizado acople bridado 6" | B103: =INSUMOS!B272 -> 1305000 | C103: 1 | D103: =C103*B103 -> 1305000 | E103: -
C104: TOTAL | D104: =SUM(D101:D103) -> 2062680 | E104: =SUM(E101:E103) -> 42.804
A106: AB-8-120
A107: Elemento | B107: Precio | C107: Cant. | D107: Parcial | E107: Peso (kg)
A108: Brida ciega de 8" 304SS | B108: =INSUMOS!B75 -> 310000 | C108: 1 | D108: =C108*B108 -> 310000 | E108: =INSUMOS!E75 -> 19.6
A109: Barra 8 " * 350 mm 304SS | B109: =INSUMOS!B10 -> 2765000 | C109: 0.35 | D109: =C109*B109 -> 967750 | E109: =C109*INSUMOS!E10 -> 89.099443
A110: Mecanizado acople bridado 8" | B110: =INSUMOS!B273 -> 1600000 | C110: 1 | D110: =C110*B110 -> 1600000 | E110: -
C111: TOTAL | D111: =SUM(D108:D110) -> 2877750 | E111: =SUM(E108:E110) -> 108.69944
A113: AB-8-120-S
A114: Elemento | B114: Precio | C114: Cant. | D114: Parcial | E114: Peso (kg)
A115: Brida ciega de 8" 316SS | B115: =INSUMOS!B93 -> 480000 | C115: 1 | D115: =C115*B115 -> 480000 | E115: =INSUMOS!E93 -> 15
A116: Barra 8 " * 350 mm 316SS | B116: =INSUMOS!B23 -> 3594500 | C116: 0.35 | D116: =C116*B116 -> 1258075 | E116: =0.35*INSUMOS!E23 -> 89.099443
...

Sheet AD
A1: AD-020-025
A2: Elemento | B2: Precio Unit | C2: Cant | D2: Parcial | E2: Peso (kg)
A3: Barra 1 1/2" * 200 mm 304SS | B3: =INSUMOS!B4 -> 87000 | C3: 0.2 | D3: =C3*B3 -> 17400 | E3: =0.2*INSUMOS!E4 -> 1.7899442
A4: Mecanizado Acople Directo 1 " | B4: =INSUMOS!B252 -> 180000 | C4: 1 | D4: =C4*B4 -> 180000 | E4: -
C5: TOTAL | D5: =SUM(D3:D4) -> 197400 | E5: =SUM(E3:E4) -> 1.7899442
A8: AD-020-032
A9: Elemento | B9: Precio Unit | C9: Cant | D9: Parcial | E9: Peso (kg)
A10: Barra 2" * 200 mm 304SS | B10: =INSUMOS!B5 -> 154000 | C10: 0.2 | D10: =C10*B10 -> 30800 | E10: =0.2*INSUMOS!E5 -> 3.182123
A11: Mecanizado Acople Directo 2" | B11: =INSUMOS!B255 -> 202000 | C11: 1 | D11: =C11*B11 -> 202000 | E11: -
C12: TOTAL | D12: =SUM(D10:D11) -> 232800 | E12: =SUM(E10:E11) -> 3.182123
A14: AD-025-032
A15: Elemento | B15: Precio Unit | C15: Cant | D15: Parcial | E15: Peso (kg)
A16: Barra 2" * 200 mm 304SS | B16: =INSUMOS!B5 -> 154000 | C16: 0.2 | D16: =C16*B16 -> 30800 | E16: =0.2*INSUMOS!E5 -> 3.182123
A17: Mecanizado Acople Directo 2" | B17: =INSUMOS!B255 -> 202000 | C17: 1 | D17: =C17*B17 -> 202000 | E17: -
C18: TOTAL | D18: =SUM(D16:D17) -> 232800 | E18: =SUM(E16:E17) -> 3.182123
A21: AD-035-050
A22: Elemento | B22: Precio Unit | C22: Cant | D22: Parcial | E22: Peso (kg)
A23: Barra 3" * 200 mm 304SS | B23: =INSUMOS!B7 -> 461000 | C23: 0.2 | D23: =C23*B23 -> 92200 | E23: =0.2*INSUMOS!E7 -> 7.1597767
A24: Mecanizado Acople Directo 3" | B24: =INSUMOS!B258 -> 266000 | C24: 1 | D24: =C24*B24 -> 266000 | E24: -
C25: TOTAL | D25: =SUM(D23:D24) -> 358200 | E25: =SUM(E23:E24) -> 7.1597767
A28: AD-025-038
A29: Elemento | B29: Precio Unit | C29: Cant | D29: Parcial | E29: Peso (kg)
A30: Barra 2" * 200 mm 304SS | B30: =INSUMOS!B5 -> 154000 | C30: 0.2 | D30: =C30*B30 -> 30800 | E30: =0.2*INSUMOS!E5 -> 3.182123
A31: Mecanizado Acople Directo 2" | B31: =INSUMOS!B255 -> 202000 | C31: 1 | D31: =C31*B31 -> 202000 | E31: -
C32: TOTAL | D32: =SUM(D30:D31) -> 232800 | E32: =SUM(E30:E31) -> 3.182123
A35: AD-035-050
A36: Elemento | B36: Precio Unit | C36: Cant | D36: Parcial | E36: Peso (kg)
A37: Barra 3" * 200 mm 304SS | B37: =INSUMOS!B7 -> 461000 | C37: 0.2 | D37: =C37*B37 -> 92200 | E37: =0.2*INSUMOS!E7 -> 7.1597767
A38: Mecanizado Acople Directo 3 " | B38: =INSUMOS!B258 -> 266000 | C38: 1 | D38: =C38*B38 -> 266000 | E38: -
C39: TOTAL | D39: =SUM(D37:D38) -> 358200 | E39: =SUM(E37:E38) -> 7.1597767
A42: AD-030-050
A43: Elemento | B43: Precio Unit | C43: Cant | D43: Parcial | E43: Peso (kg)
A44: Barra 3" * 200 mm 304SS | B44: =INSUMOS!B7 -> 461000 | C44: 0.2 | D44: =C44*B44 -> 92200 | E44: =0.2*INSUMOS!E7 -> 7.1597767
A45: Mecanizado Acople Directo 3" | B45: =INSUMOS!B258 -> 266000 | C45: 1 | D45: =C45*B45 -> 266000 | E45: -
C46: TOTAL | D46: =SUM(D44:D45) -> 358200 | E46: =SUM(E44:E45) -> 7.1597767
A48: AD-020-038
A49: Elemento | B49: Precio Unit | C49: Cant | D49: Parcial | E49: Peso (kg)
A50: Barra 2" * 112 mm 304SS | B50: =INSUMOS!B5 -> 154000 | C50: 0.15 | D50: =C50*B50 -> 23100 | E50: =0.2*INSUMOS!E5 -> 3.182123
A51: Mecanizado Acople Directo 2" | B51: =INSUMOS!B255 -> 202000 | C51: 1 | D51: =C51*B51 -> 202000 | E51: -
C52: TOTAL | D52: =SUM(D50:D51) -> 225100 | E52: =SUM(E50:E51) -> 3.182123
A54: AD-020-025-S
A55: Elemento | B55: Precio Unit | C55: Cant | D55: Parcial | E55: Peso (kg)
A56: Barra 1 1/2" * 200 mm 316SS | B56: =INSUMOS!B15 -> 140000 | C56: 0.2 | D56: =C56*B56 -> 28000 | E56: =C56*INSUMOS!E15 -> 1.7899442
A57: Mecanizado Acople Directo 1 " | B57: =INSUMOS!B252 -> 180000 | C57: 1 | D57: =C57*B57 -> 180000 | E57: -
C58: TOTAL | D58: =SUM(D56:D57) -> 208000 | E58: =SUM(E56:E57) -> 1.7899442
A60: AD-014-025
A61: Elemento | B61: Precio Unit | C61: Cant | D61: Parcial | E61: Peso (kg)
A62: Barra 1 1/2" * 200 mm 304SS | B62: =INSUMOS!B4 -> 87000 | C62: 0.2 | D62: =C62*B62 -> 17400 | E62: =C62*INSUMOS!E4 -> 1.7899442
A63: Mecanizado Acople Directo 1 1/2 " | B63: =INSUMOS!B252 -> 180000 | C63: 1 | D63: =C63*B63 -> 180000 | E63: -
C64: TOTAL | D64: =SUM(D62:D63) -> 197400 | E64: =SUM(E62:E63) -> 1.7899442
A66: AD-014-025-S
A67: Elemento | B67: Precio Unit | C67: Cant | D67: Parcial | E67: Peso (kg)
A68: Barra 1 1/2" * 200 mm 316SS | B68: =INSUMOS!B15 -> 140000 | C68: 0.2 | D68: =C68*B68 -> 28000 | E68: =C68*INSUMOS!E15 -> 1.7899442
A69: Mecanizado Acople Directo 1 " | B69: =INSUMOS!B252 -> 180000 | C69: 1 | D69: =C69*B69 -> 180000 | E69: -
C70: TOTAL | D70: =SUM(D68:D69) -> 208000 | E70: =SUM(E68:E69) -> 1.7899442
A72: AD-018-038
A73: Elemento | B73: Precio Unit | C73: Cant | D73: Parcial | E73: Peso (kg)
A74: Barra 2" * 200 mm 304SS | B74: =INSUMOS!B5 -> 154000 | C74: 0.2 | D74: =C74*B74 -> 30800 | E74: =C74*INSUMOS!E5 -> 3.182123
A75: Mecanizado Acople Directo 2 " | B75: =INSUMOS!B255 -> 202000 | C75: 1 | D75: =C75*B75 -> 202000 | E75: -
C76: TOTAL | D76: =SUM(D74:D75) -> 232800 | E76: =SUM(E74:E75) -> 3.182123
A78: AD-018-025
A79: Elemento | B79: Precio Unit | C79: Cant | D79: Parcial | E79: Peso (kg)
A80: Barra 1 1/2" * 200 mm 304SS | B80: =INSUMOS!B4 -> 87000 | C80: 0.2 | D80: =C80*B80 -> 17400 | E80: =C80*INSUMOS!E4 -> 1.7899442
A81: Mecanizado Acople Directo 1 " | B81: =INSUMOS!B252 -> 180000 | C81: 1 | D81: =C81*B81 -> 180000 | E81: -
C82: TOTAL | D82: =SUM(D80:D81) -> 197400 | E82: =SUM(E80:E81) -> 1.7899442
A84: AD-018-032
A85: Elemento | B85: Precio Unit | C85: Cant | D85: Parcial | E85: Peso (kg)
A86: Barra 2" * 200 mm 304SS | B86: =INSUMOS!B5 -> 154000 | C86: 0.2 | D86: =C86*B86 -> 30800 | E86: =C86*INSUMOS!E5 -> 3.182123
A87: Mecanizado Acople Directo 2" | B87: =INSUMOS!B255 -> 202000 | C87: 1 | D87: =C87*B87 -> 202000 | E87: -
C88: TOTAL | D88: =SUM(D86:D87) -> 232800 | E88: =SUM(E86:E87) -> 3.182123
A90: AD-025-050
A91: Elemento | B91: Precio Unit | C91: Cant | D91: Parcial | E91: Peso (kg)
A92: Barra 3" * 200 mm 304SS | B92: =INSUMOS!B7 -> 461000 | C92: 0.2 | D92: =C92*B92 -> 92200 | E92: =C92*INSUMOS!E7 -> 7.1597767
A93: Mecanizado Acople Directo 3" | B93: =INSUMOS!B258 -> 266000 | C93: 1 | D93: =C93*B93 -> 266000 | E93: -
C94: TOTAL | D94: =SUM(D92:D93) -> 358200 | E94: =SUM(E92:E93) -> 7.1597767
A96: AD-030-038
A97: Elemento | B97: Precio Unit | C97: Cant | D97: Parcial | E97: Peso (kg)
A98: Barra 2" * 200 mm 304SS | B98: =INSUMOS!B5 -> 154000 | C98: 0.2 | D98: =C98*B98 -> 30800 | E98: =C98*INSUMOS!E5 -> 3.182123
A99: Mecanizado Acople Directo 2" | B99: =INSUMOS!B255 -> 202000 | C99: 1 | D99: =C99*B99 -> 202000 | E99: -
C100: TOTAL | D100: =SUM(D98:D99) -> 232800 | E100: =SUM(E98:E99) -> 3.182123
A102: AD-025-025
A103: Elemento | B103: Precio Unit | C103: Cant | D103: Parcial | E103: Peso (kg)
A104: Barra 1 1/2" * 200 mm 304SS | B104: =INSUMOS!B4 -> 87000 | C104: 0.2 | D104: =C104*B104 -> 17400 | E104: =C104*INSUMOS!E4 -> 1.7899442
A105: Mecanizado Acople Directo 1 " | B105: =INSUMOS!B252 -> 180000 | C105: 1 | D105: =C105*B105 -> 180000 | E105: -
C106: TOTAL | D106: =SUM(D104:D105) -> 197400 | E106: =SUM(E104:E105) -> 1.7899442
A108: AD-035-038
A109: Elemento | B109: Precio Unit | C109: Cant | D109: Parcial | E109: Peso (kg)
A110: Barra 2" * 200 mm 304SS | B110: =INSUMOS!B5 -> 154000 | C110: 0.2 | D110: =C110*B110 -> 30800 | E110: =C110*INSUMOS!E5 -> 3.182123
A111: Mecanizado Acople Directo 2" | B111: =INSUMOS!B255 -> 202000 | C111: 1 | D111: =C111*B111 -> 202000 | E111: -
C112: TOTAL | D112: =SUM(D110:D111) -> 232800 | E112: =SUM(E110:E111) -> 3.182123
A114: AD-050-050
A115: Elemento | B115: Precio Unit | C115: Cant | D115: Parcial | E115: Peso (kg)
A116: Barra 4" * 200 mm 304SS | B116: =INSUMOS!B8 -> 563000 | C116: 0.3 | D116: =C116*B116 -> 168900 | E116: =C116*INSUMOS!E8 -> 19.092738
A117: Mecanizado Acople Directo 2 PARTIDO " | B117: =INSUMOS!B256 -> 280000 | C117: 1 | D117: =C117*B117 -> 280000 | E117: -
C118: TOTAL | D118: =SUM(D116:D117) -> 448900 | E118: =SUM(E116:E117) -> 19.092738
A120: AD-018-032-S
A121: Elemento | B121: Precio Unit | C121: Cant | D121: Parcial | E121: Peso (kg)
A122: Barra 2" * 200 mm 316SS | B122: =INSUMOS!B16 -> 240000 | C122: 0.2 | D122: =C122*B122 -> 48000 | E122: =C122*INSUMOS!E5 -> 3.182123
A123: Mecanizado Acople Directo 2" | B123: =INSUMOS!B255 -> 202000 | C123: 1 | D123: =C123*B123 -> 202000 | E123: -
C124: TOTAL | D124: =SUM(D122:D123) -> 250000 | E124: =SUM(E122:E123) -> 3.182123
...

Sheet P
A1: P2-BBM
A2: Elemento | B2: Precio Unit. | C2: Cant. | D2: Parcial | E2: Peso (kg)
A3: Material Propelas T200 | B3: =INSUMOS!B128 -> 120000 | C3: 1 | D3: =C3*B3 -> 120000 | E3: =INSUMOS!E128 -> 0.97
A4: Barra de 1 1/2" * 0,15 m 304SS | B4: =INSUMOS!B4 -> 87000 | C4: 0.15 | D4: =C4*B4 -> 13050 | E4: =0.15*INSUMOS!E4 -> 1.3424581
A5: Maquinado de manzana de 1 1/2" | B5: =INSUMOS!B296 -> 178200 | C5: 1 | D5: =C5*B5 -> 178200 | E5: -
A6: Mecanizado Propelas T200 | B6: =INSUMOS!B286 -> 50000 | C6: 1 | D6: =C6*B6 -> 50000
A7: SandBlasting T200 | B7: =INSUMOS!B300 -> 30000 | C7: 1 | D7: =C7*B7 -> 30000
C8: TOTAL | D8: =SUM(D3:D7) -> 391250 | E8: =SUM(E3:E7) -> 2.3124581
A11: P2-DBM
A12: Elemento | B12: Precio Unit. | C12: Cant. | D12: Parcial | E12: Peso (kg)
A13: Material Propelas T350 | B13: =INSUMOS!B130 -> 130000 | C13: 1 | D13: =C13*B13 -> 130000 | E13: =INSUMOS!E130 -> 2.91
A14: Barra de 1 1/2" * 0,15 m 304SS | B14: =INSUMOS!B4 -> 87000 | C14: 0.15 | D14: =C14*B14 -> 13050 | E14: =0.15*INSUMOS!E4 -> 1.3424581
A15: Maquinado de manzana de 1 1/2" | B15: =INSUMOS!B296 -> 178200 | C15: 1 | D15: =C15*B15 -> 178200 | E15: -
A16: Mecanizado Propelas T350 | B16: =INSUMOS!B288 -> 80000 | C16: 1 | D16: =C16*B16 -> 80000
A17: SandBlasting T350 | B17: =INSUMOS!B302 -> 40000 | C17: 1 | D17: =C17*B17 -> 40000
C18: TOTAL | D18: =SUM(D13:D17) -> 441250 | E18: =SUM(E13:E17) -> 4.2524581
A21: P2-DCM
A22: Elemento | B22: Precio Unit. | C22: Cant. | D22: Parcial | E22: Peso (kg)
A23: Material Propelas T350 | B23: =INSUMOS!B130 -> 130000 | C23: 1 | D23: =C23*B23 -> 130000 | E23: =INSUMOS!E130 -> 2.91
A24: Barra de 2" * 0,15 m 304SS | B24: =INSUMOS!B5 -> 154000 | C24: 0.15 | D24: =C24*B24 -> 23100 | E24: =0.15*INSUMOS!E5 -> 2.3865922
A25: Maquinado de manzana de 2" | B25: =INSUMOS!B297 -> 200000 | C25: 1 | D25: =C25*B25 -> 200000 | E25: -
A26: Mecanizado Propelas T350 | B26: =INSUMOS!B288 -> 80000 | C26: 1 | D26: =C26*B26 -> 80000
A27: SandBlasting T350 | B27: =INSUMOS!B302 -> 40000 | C27: 1 | D27: =C27*B27 -> 40000
C28: TOTAL | D28: =SUM(D23:D27) -> 473100 | E28: =SUM(E23:E27) -> 5.2965922
A31: P2-HCM
A32: Elemento | B32: Precio Unit. | C32: Cant. | D32: Parcial | E32: Peso (kg)
A33: Material Propelas T550 | B33: =INSUMOS!B132 -> 170000 | C33: 1 | D33: =C33*B33 -> 170000 | E33: =INSUMOS!E132 -> 4.08
A34: Barra de 2" * 0,15 m 304SS | B34: =0.15*INSUMOS!B5 -> 23100 | C34: 0.15 | D34: =C34*B34 -> 3465 | E34: =0.15*INSUMOS!E5 -> 2.3865922
A35: Maquinado de manzana de 2" | B35: =INSUMOS!B297 -> 200000 | C35: 1 | D35: =C35*B35 -> 200000 | E35: -
A36: Mecanizado Propelas T550 | B36: =INSUMOS!B290 -> 130000 | C36: 1 | D36: =C36*B36 -> 130000
A37: SandBlasting T550 | B37: =INSUMOS!B304 -> 60000 | C37: 1 | D37: =C37*B37 -> 60000
C38: TOTAL | D38: =SUM(D33:D37) -> 563465 | E38: =SUM(E33:E37) -> 6.4665922
A41: P2-BCM
A42: Elemento | B42: Precio Unit. | C42: Cant. | D42: Parcial | E42: Peso (kg)
A43: Material Propelas T200 | B43: =INSUMOS!B128 -> 120000 | C43: 1 | D43: =C43*B43 -> 120000 | E43: =INSUMOS!E128 -> 0.97
A44: Barra de 2" * 0,15 m 304SS | B44: =INSUMOS!B5 -> 154000 | C44: 0.15 | D44: =C44*B44 -> 23100 | E44: =0.15*INSUMOS!E5 -> 2.3865922
A45: Maquinado de manzana de 2" | B45: =INSUMOS!B297 -> 200000 | C45: 1 | D45: =C45*B45 -> 200000 | E45: -
A46: Mecanizado Propelas T200 | B46: =INSUMOS!B286 -> 50000 | C46: 1 | D46: =C46*B46 -> 50000
A47: SandBlasting T200 | B47: =INSUMOS!B300 -> 30000 | C47: 1 | D47: =C47*B47 -> 30000
C48: TOTAL | D48: =SUM(D43:D47) -> 423100 | E48: =SUM(E43:E47) -> 3.3565922
A51: P2-ABM
A52: Elemento | B52: Precio Unit. | C52: Cant. | D52: Parcial | E52: Peso (kg)
A53: Material Propelas T160 | B53: =INSUMOS!B127 -> 110000 | C53: 1 | D53: =C53*B53 -> 110000 | E53: =INSUMOS!E127 -> 0.9
A54: Barra de 1 1/2" * 0,15 m 304SS | B54: =INSUMOS!B4 -> 87000 | C54: 0.15 | D54: =C54*B54 -> 13050 | E54: =0.15*INSUMOS!E4 -> 1.3424581
A55: Maquinado de manzana de 1 1/2" | B55: =INSUMOS!B296 -> 178200 | C55: 1 | D55: =C55*B55 -> 178200 | E55: -
A56: Mecanizado Propelas T160 | B56: =INSUMOS!B285 -> 50000 | C56: 1 | D56: =C56*B56 -> 50000
A57: SandBlasting T160 | B57: =INSUMOS!B299 -> 30000 | C57: 1 | D57: =C57*B57 -> 30000
C58: TOTAL | D58: =SUM(D53:D57) -> 381250 | E58: =SUM(E53:E57) -> 2.2424581
A61: P2-GDMS
A62: Elemento | B62: Precio Unit. | C62: Cant. | D62: Parcial | E62: Peso (kg)
A63: Material Propelas T500 316SS | B63: =INSUMOS!B139 -> 195000 | C63: 1 | D63: =C63*B63 -> 195000 | E63: =INSUMOS!E139 -> 4
A64: Barra de 2" * 0,15 m 316SS | B64: =INSUMOS!B16 -> 240000 | C64: 0.15 | D64: =C64*B64 -> 36000 | E64: =0.15*INSUMOS!E16 -> 2.3865922
A65: Maquinado de manzana de 2" | B65: =INSUMOS!B297 -> 200000 | C65: 1 | D65: =C65*B65 -> 200000
A66: Mecanizado Propelas T500 | B66: =INSUMOS!B289 -> 100000 | C66: 1 | D66: =C66*B66 -> 100000
A67: SandBlasting T500 | B67: =INSUMOS!B303 -> 50000 | C67: 1 | D67: =C67*B67 -> 50000
C68: TOTAL | D68: =SUM(D63:D67) -> 581000 | E68: =SUM(E63:E67) -> 6.3865922
A71: P3-GDM
A72: Elemento | B72: Precio Unit. | C72: Cant. | D72: Parcial | E72: Peso (kg)
A73: Material Propelas CT500 | B73: =INSUMOS!B149 -> 150000 | C73: 1 | D73: =C73*B73 -> 150000 | E73: =INSUMOS!E149 -> 4.8
A74: Barra de 2" * 0,15 m 304SS | B74: =INSUMOS!B5 -> 154000 | C74: 0.15 | D74: =C74*B74 -> 23100 | E74: =0.15*INSUMOS!E5 -> 2.3865922
A75: Maquinado de manzana de 2" | B75: =INSUMOS!B297 -> 200000 | C75: 1 | D75: =C75*B75 -> 200000
A76: Mecanizado Propelas CT500 | B76: =INSUMOS!B350 -> 150000 | C76: 1 | D76: =C76*B76 -> 150000
A77: SandBlasting CT500 | B77: =INSUMOS!B313 -> 50000 | C77: 1 | D77: =C77*B77 -> 50000
C78: TOTAL | D78: =SUM(D73:D77) -> 573100 | E78: =SUM(E73:E77) -> 7.1865922
A81: P3-GDMS
A82: Elemento | B82: Precio Unit. | C82: Cant. | D82: Parcial | E82: Peso (kg)
A83: Material Propelas CT500 316SS | B83: =INSUMOS!B163 -> 210000 | C83: 1 | D83: =C83*B83 -> 210000 | E83: =INSUMOS!E163 -> 4.8
A84: Barra de 2" * 0,15 m 316SS | B84: =INSUMOS!B16 -> 240000 | C84: 0.15 | D84: =C84*B84 -> 36000 | E84: =0.15*INSUMOS!E16 -> 2.3865922
A85: Maquinado de manzana de 2" | B85: =INSUMOS!B297 -> 200000 | C85: 1 | D85: =C85*B85 -> 200000
A86: Mecanizado Propelas CT500 | B86: =INSUMOS!B350 -> 150000 | C86: 1 | D86: =C86*B86 -> 150000
A87: SandBlasting CT500 | B87: =INSUMOS!B313 -> 50000 | C87: 1 | D87: =C87*B87 -> 50000
C88: TOTAL | D88: =SUM(D83:D87) -> 646000 | E88: =SUM(E83:E87) -> 7.1865922
A91: P3-CCM
A92: Elemento | B92: Precio Unit. | C92: Cant. | D92: Parcial | E92: Peso (kg)
A93: Material Propelas CT300 304SS | B93: =INSUMOS!B147 -> 105000 | C93: 1 | D93: =C93*B93 -> 105000 | E93: =INSUMOS!E147 -> 1.6
A94: Barra de 2" * 0,15 m 304SS | B94: =INSUMOS!B5 -> 154000 | C94: 0.15 | D94: =C94*B94 -> 23100 | E94: =0.15*INSUMOS!E5 -> 2.3865922
A95: Maquinado de manzana de 2" | B95: =INSUMOS!B297 -> 200000 | C95: 1 | D95: =C95*B95 -> 200000 | E95: -
A96: Mecanizado Propelas CT300 | B96: =INSUMOS!B348 -> 120000 | C96: 1 | D96: =C96*B96 -> 120000
A97: SandBlasting CT300 | B97: =INSUMOS!B311 -> 35000 | C97: 1 | D97: =C97*B97 -> 35000
C98: TOTAL | D98: =SUM(D93:D97) -> 483100 | E98: =SUM(E93:E97) -> 3.9865922
A101: P3-MIC
A102: Elemento | B102: Precio Unit. | C102: Cant. | D102: Parcial | E102: Peso (kg)
A103: Material Propelas CT1200 304SS | B103: =INSUMOS!B154 -> 850000 | C103: 1 | D103: =C103*B103 -> 850000 | E103: =INSUMOS!E154 -> 28.5
A104: CASQUETE 4" TRIPALA 304SS | B104: =INSUMOS!B210 -> 325000 | C104: 1 | D104: =C104*B104 -> 325000 | E104: =INSUMOS!E210 -> 8
A105: Mecanizado Propelas CT1200 | B105: =INSUMOS!B355 -> 600000 | C105: 1 | D105: =C105*B105 -> 600000 | E105: -
A106: Doblado Propelas CT1200 | B106: =INSUMOS!B374 -> 260000 | C106: 1 | D106: =C106*B106 -> 260000
A107: SandBlasting CT1200 | B107: =INSUMOS!B318 -> 120000 | C107: 1 | D107: =C107*B107 -> 120000
C108: TOTAL | D108: =SUM(D103:D107) -> 2155000 | E108: =SUM(E103:E107) -> 36.5
A111: P3-EDM
A112: Elemento | B112: Precio Unit. | C112: Cant. | D112: Parcial | E112: Peso (kg)
A113: Material Propelas CT400 304SS | B113: =INSUMOS!B148 -> 120000 | C113: 1 | D113: =C113*B113 -> 120000 | E113: =INSUMOS!E148 -> 3.2
A114: Barra de 2" * 0,15 m 304SS | B114: =INSUMOS!B5 -> 154000 | C114: 0.2 | D114: =C114*B114 -> 30800 | E114: =0.15*INSUMOS!E5 -> 2.3865922
A115: Maquinado de manzana de 2" | B115: =INSUMOS!B297 -> 200000 | C115: 1 | D115: =C115*B115 -> 200000 | E115: -
A116: Mecanizado Propelas CT400 | B116: =INSUMOS!B349 -> 120000 | C116: 1 | D116: =C116*B116 -> 120000
A117: SandBlasting CT400 | B117: =INSUMOS!B312 -> 45000 | C117: 1 | D117: =C117*B117 -> 45000
C118: TOTAL | D118: =SUM(D113:D117) -> 515800 | E118: =SUM(E113:E117) -> 5.5865922
A121: P2-JEM
A122: Elemento | B122: Precio Unit. | C122: Cant. | D122: Parcial | E122: Peso (kg)
A123: Material Propelas T700 | B123: =INSUMOS!B133 -> 230000 | C123: 1 | D123: =C123*B123 -> 230000 | E123: =INSUMOS!E133 -> 16.63
A124: Barra de 3" * 0,15 m 304SS | B124: =INSUMOS!B7 -> 461000 | C124: 0.15 | D124: =C124*B124 -> 69150 | E124: =0.15*INSUMOS!E7 -> 5.3698325
...

Sheet INSUMOS
A1: BARRAS MACIZAS 304SS | B1: VALOR / m | C1: ULTIMA COTIZACION | D1: EMPRESA | E1: PESO POR METRO (KG)
A2: 1 " | B2: 39000 | C2: 42426 | D2: CORTEACEROS | E2: =PI()*0.0254^2/4*7850 -> 3.9776537
A3: 1 1/4" | B3: 64000 | C3: 42426 | D3: CORTEACEROS | E3: =PI()*(1.25*0.0254)^2/4*7850 -> 6.2150839
A4: 1 1/2" | B4: 87000 | C4: 42426 | D4: CORTEACEROS | E4: =PI()*(1.5*0.0254)^2/4*7850 -> 8.9497208
A5: 2" | B5: 154000 | C5: 42426 | D5: CORTEACEROS | E5: =PI()*(2*0.0254)^2/4*7850 -> 15.910615
A6: 2 1/2" | B6: 225000 | C6: 42426 | D6: CORTEACEROS | E6: =PI()*(2.5*0.0254)^2/4*7850 -> 24.860336
A7: 3" | B7: 461000 | C7: 42444 | D7: IMPORINOX | E7: =PI()*(3*0.0254)^2/4*7850 -> 35.798883
A8: 4" | B8: 563000 | C8: 42429 | D8: CORTEACEROS | E8: =PI()*(4*0.0254)^2/4*7850 -> 63.642459
A9: 6" | B9: 1267000 | C9: 42474 | D9: CORTEACEROS | E9: =PI()*(6*0.0254)^2/4*7850 -> 143.19553
A10: 8" | B10: 2765000 | C10: 42479 | D10: CORTEACEROS | E10: =PI()*(8*0.0254)^2/4*7850 -> 254.56984
A11: 10" | B11: 4000000 | C11: 42697 | D11: IMPORINOX | E11: =PI()*(10*0.0254)^2/4*7850 -> 397.76537
A12: BARRAS MACIZAS 316SS | B12: VALOR / m | C12: ULTIMA COTIZACION | D12: EMPRESA | E12: PESO POR METRO (KG)
A13: 1" | B13: 80000 | C13: SUPUESTO | D13: IMPORINOX | E13: =E2 -> 3.9776537
A14: 1 1/4" | B14: 120000 | C14: SUPUESTO | D14: IMPORINOX | E14: =E3 -> 6.2150839
A15: 1 1/2" | B15: 140000 | C15: 42460 | D15: IMPORINOX | E15: =E4 -> 8.9497208
A16: 2" | B16: 240000 | C16: 42444 | D16: IMPORINOX | E16: =E5 -> 15.910615
A17: 2 1/4" | B17: 265000 | C17: 42444 | D17: IMPORINOX | E17: =PI()*(2.25*0.0254)^2/4*7850 -> 20.136872
A18: 2 1/2" | B18: 322000 | C18: 42444 | D18: IMPORINOX | E18: =E6 -> 24.860336
A19: 3" | B19: 461000 | C19: 42444 | D19: IMPORINOX | E19: =E7 -> 35.798883
A20: 3 1/2" | B20: 625000 | C20: 42444 | D20: IMPORINOX | E20: =PI()*(3.5*0.0254)^2/4*7850 -> 48.726258
A21: 4" | B21: 720000 | C21: 42521 | D21: IMPORINOX | E21: =PI()*(4*0.0254)^2/4*7850 -> 63.642459
A22: 6" | B22: =B21*POWER(6/4,2)*1.2 -> 1944000 | C22: 42528 | D22: Estimado extrapolacion | E22: 143.2
A23: 8" | B23: =1.3*B10 -> 3594500 | C23: 42521 | D23: IMPORINOX | E23: =PI()*(8*0.0254)^2/4*7850 -> 254.56984
A24: 10" | B24: 6500000 | C24: ESTIMADO | D24: IMPORINOX | E24: =PI()*(10*0.0254)^2/4*7850 -> 397.76537
A25: BARRAS MACIZAS 4140 | B25: VALOR / m | C25: ULTIMA COTIZACION | D25: EMPRESA | E25: PESO POR METRO (KG)
A26: 1 1/4" | B26: 35500 | C26: 42579 | D26: ACEROSCOL | E26: =PI()*(1.25*0.0254)^2/4*7850 -> 6.2150839
A27: 1 3/8" | B27: 42500 | C27: 42579 | D27: ACEROSCOL | E27: =PI()*(1.375*0.0254)^2/4*7850 -> 7.5202515
A28: BARRAS MACIZAS 1020 | B28: VALOR / m | C28: ULTIMA COTIZACION | D28: EMPRESA | E28: PESO POR METRO (KG)
A29: 4 ½” | B29: 340000 | C29: 42460 | D29: IMPORINOX | E29: =PI()*(4.5*0.0254)^2/4*7850 -> 80.547488
A30: 6” | B30: 550000 | C30: 2015 | D30: IMPORINOX | E30: =PI()*(6*0.0254)^2/4*7850 -> 143.19553
A31: BARRAS PERFORADAS 1518 | B31: VALOR / m | C31: ULTIMA COTIZACION | D31: EMPRESA | E31: PESO POR METRO (KG)
A32: D ext: 102 mm D in: 80 mm | B32: 112000 | C32: 42550 | D32: ACEROSCOL | E32: =(PI()*(51/1000)^2-PI()*(40/1000)^2)*7850 -> 24.686164
A33: D ext: 76 mm D in: 42 mm | B33: 112000 | C33: 42550 | D33: ACEROSCOL | E33: =(PI()*(38/1000)^2-PI()*(21/1000)^2)*7850 -> 24.735487
A34: D ext: 101 mm D in: 51 mm | B34: 212000 | C34: 42550 | D34: ACEROSCOL | E34: =(PI()*(50.5/1000)^2-PI()*(25.5/1000)^2)*7850 -> 46.856854
A35: BARRAS MACIZAS 1045 | B35: VALOR / m | C35: ULTIMA COTIZACION | D35: EMPRESA | E35: PESO POR METRO (KG)
A36: 3" | B36: 159000 | C36: 42550 | D36: ACEROSCOL | E36: =PI()*(1.5*25.4/1000)^2*7850 -> 35.798883
A37: TUBOS SCH 10 316L | B37: VALOR 5,8 m | C37: ULTIMA COTIZACION | D37: EMPRESA | E37: PESO POR METRO (KG)
A38: 1 1/4" | B38: 272600 | C38: 42579 | D38: TUVACOL | E38: =(PI()*(1.66*25.4/1000)^2-PI()*((1.66-2*0.109)*25.4/1000)^2)*7850/4 -> 2.6898326
A39: 2" | B39: =58600*5.8 -> 339880 | C39: 42550 | D39: ACEROSCOL | E39: =(PI()*(2.375*25.4/1000)^2-PI()*((2.375-2*0.109)*25.4/1000)^2)*7850/4 -> 3.9298264
A40: 3" | B40: =78000*5.8 -> 452400 | C40: 42550 | D40: ACEROSCOL | E40: =(PI()*(3.5*25.4/1000)^2-PI()*((3.5-2*0.12)*25.4/1000)^2)*7850/4 -> 6.4533454
A41: 4" | B41: =128800*5.8 -> 747040 | C41: 42550 | D41: ACEROSCOL | E41: =(PI()*(4.5*25.4/1000)^2-PI()*((4.5-2*0.12)*25.4/1000)^2)*7850/4 -> 8.3626192
A42: 6" | B42: =222000*5.8 -> 1287600 | C42: 42550 | D42: ACEROSCOL | E42: =(PI()*(6.625*25.4/1000)^2-PI()*((6.625-2*0.134)*25.4/1000)^2)*7850/4 -> 13.838957
A43: TUBOS SCH 40 304SS | B43: VALOR 5,8 m | C43: ULTIMA COTIZACION | D43: EMPRESA | E43: PESO POR METRO (KG)
A44: 1 1/4" | B44: 240000 | C44: 42878 | D44: SUMIVALLE | E44: 3
A45: 1 1/2" | B45: 250000 | C45: 42878 | D45: SUMIVALLE | E45: 3.2
A46: 2" | B46: =400000*1.1 -> 440000 | C46: 42627 | D46: SUMIVALLE | E46: =(PI()*(2.375*25.4/1000)^2-PI()*((2.375-2*0.154)*25.4/1000)^2)*7850/4 -> 5.4419712 | H46: TUBOS
A47: 2 1/2" | B47: =580000*1.1 -> 638000 | C47: 42192 | D47: TUVACOL | E47: 8.63 | H47: CON
A48: 3" | B48: =683240*1.1 -> 751564 | C48: 42426 | D48: TUVACOL | E48: 11.3 | H48: 1.1
A49: 4" | B49: =957000*1.1 -> 1052700 | C49: 42426 | D49: TUVACOL | E49: 16.09 | H49: POR
A50: 5" | B50: 1333000 | C50: 42753 | D50: CORTEACEROS | E50: 21.8
A51: 6" | B51: =2708000*1.1 -> 2978800 | C51: 42426 | D51: TUVACOL | E51: 28.2 | H51: CAMBIO
A52: 8" | B52: =4245000*1.1 -> 4669500 | C52: 42447 | D52: TUVACOL | E52: 42.6 | H52: DE
A53: 10" | B53: =5300000*1.1 -> 5830000 | C53: 42696 | D53: IMPORINOX | E53: 60.3 | H53: AÑO
A54: TUBOS SCH 40 316SS | B54: VALOR 5,8 m | C54: ULTIMA COTIZACION | D54: EMPRESA | E54: PESO POR METRO (KG)
A55: 1 1/4" | B55: 300000 | C55: 42878 | D55: SUMIVALLE | E55: 2.9
A56: 1 1/2" | B56: 310000 | C56: 42878 | D56: SUMIVALLE | E56: 3.2
A57: 2" | B57: 1050000 | C57: 42478 | D57: TUVACOL | E57: 5.4
A58: 2 1/2" | B58: =B47*2 -> 1276000 | C58: 42478 | D58: TUVACOL | E58: 8.6
A59: 3" | B59: 1320000 | C59: 42478 | D59: TUVACOL | E59: =E48 -> 11.3
A60: 4" | B60: =876000*2 -> 1752000 | C60: 42402 | D60: TUVACOL | E60: =E49 -> 16.09
A61: 6" | B61: 3600000 | C61: 42437 | D61: TUVACOL | E61: =E51 -> 28.2
A62: 8" | B62: 4770500 | C62: 42478 | D62: TUVACOL | E62: =E52 -> 42.6
A63: 10" | B63: 14500000 | C63: 42696 | D63: TUVACOL | E63: =E53 -> 60.3
A64: TUBOS SCH 40 A53 | B64: VALOR 5,8 m | C64: ULTIMA COTIZACION | D64: EMPRESA | E64: PESO POR METRO (KG)
A65: 6 " | B65: 448340 | C65: 42503 | D65: TUVACOL | E65: =E51 -> 28.2
A66: 8" | B66: =B65*8/6 -> 597786.67 | C66: ESTIMADO | D66: TUVACOL | E66: =E62 -> 42.6
A67: BRIDAS CIEGAS 304SS | B67: PRECIO | C67: ULTIMA COTIZACION | D67: EMPRESA | E67: PESO UNITARIO (KG)
A68: 1 1/4" | B68: 60000 | C68: ESTIMADO | D68: TUVACOL | E68: 1.7
A69: 1 1/2" | B69: 65000 | C69: ESTIMADO | D69: TUVACOL | E69: 2
A70: 2 " | B70: 80000 | C70: 42426 | D70: TUVACOL | E70: 3
A71: 2 1/2" | B71: 80000 | C71: 42426 | D71: TUVACOL | E71: 3
A72: 3" | B72: 98250 | C72: 42426 | D72: TUVACOL | E72: 4.93
A73: 4" | B73: 148500 | C73: 42426 | D73: TUVACOL | E73: 7
A74: 6" | B74: 212000 | C74: 42425 | D74: TUVACOL | E74: 11.3
A75: 8" | B75: 310000 | C75: 42447 | D75: TUVACOL | E75: 19.6
A76: 10" | B76: 508000 | C76: 42696 | D76: CASAVAL | E76: 23
A77: BRIDA SLIP ON 304SS | B77: PRECIO | C77: ULTIMA COTIZACION | D77: EMPRESA | E77: PESO UNITARIO (KG)
A78: 2" | B78: =75000 -> 75000 | C78: ESTIMADO | D78: TUVACOL | E78: 3
A79: 2 1/2" | B79: 82000 | C79: 42430 | D79: TUVACOL | E79: 3.28
A80: 3" | B80: 78000 | C80: 42426 | D80: TUVACOL | E80: 3.85
A81: 4" | B81: 115000 | C81: 42426 | D81: TUVACOL | E81: 5.3
A82: 5" | B82: 130000 | C82: 42753 | D82: TUVACOL | E82: 9.5
A83: 6" | B83: 116100 | C83: 42656 | D83: CASAVAL | E83: 11.3
A84: 8" | B84: 310000 | C84: 42447 | D84: TUVACOL | E84: 12.1
A85: 10" | B85: 350000 | C85: 42696 | D85: IMPORINOX | E85: 14
A86: BRIDA CIEGA 316SS | B86: PRECIO | C86: ULTIMA COTIZACION | D86: EMPRESA | E86: PESO UNITARIO (KG)
A87: 1 1/2" | B87: 80000 | C87: ESTIMADO | D87: TUVACOL | E87: 2
A88: 2" | B88: 120000 | C88: ESTIMADO | D88: TUVACOL | E88: 3
A89: 2 1/2" | B89: 130000 | C89: ESTIMADO | D89: TUVACOL | E89: 3.28
A90: 3" | B90: =190000*1.1 -> 209000 | C90: 42639 | D90: ASUMINCOL | E90: 4.93
A91: 4" | B91: =296000*1.1 -> 325600 | C91: 42639 | D91: ASUMINCOL | E91: 6.8
A92: 6" | B92: 330000 | C92: 42437 | D92: TUVACOL | E92: 11.3
A93: 8" | B93: 480000 | C93: 42437 | D93: TUVACOL | E93: =15 -> 15
A94: 10" | B94: 871500 | C94: 42696 | D94: TUVACOL | E94: 23
A95: BRIDA SLIP ON 316SS | B95: PRECIO | C95: ULTIMA COTIZACION | D95: EMPRESA | E95: PESO UNITARIO (KG)
A96: 1 1/2" | B96: 45000 | C96: 42878 | D96: SUMIVALLE | E96: 2
A97: 2 1/2" | B97: 99000 | C97: 42444 | D97: IMPORINOX | E97: 3.28
A98: 3" | B98: =169400*1.1 -> 186340 | C98: 42640 | D98: ASUMINCOL | E98: 3.85
A99: 4" | B99: =247000*1.1 -> 271700 | C99: 42640 | D99: ASUMINCOL | E99: 6.2
A100: 6" | B100: 240000 | C100: 42437 | D100: TUVACOL | E100: 7.45
...

Sheet P. PARTES
A1: PROPELAS
A2: COD | B2: PRECIO | C2: DESCRIPCION
A3: =P!A51 -> P2-ABM | B3: =P!D58 -> 381250 | C3: Propela Turbina 160 mm eje 1" con Manzana Acero 304SS
A4: =P!A1 -> P2-BBM | B4: =P!D8 -> 391250 | C4: Propela Turbina 200 mm eje 1" con Manzana Acero 304SS
A5: =P!A1459 -> P2-BBMS | B5: =P!D1466 -> 435200 | C5: Propela Turbina 200 mm eje 1" con Manzana Acero 316SS
A6: =P!A41 -> P2-BCM | B6: =P!D48 -> 423100 | C6: Propela Turbina 200 mm eje 1 1/4 " con Manzana Acero 304SS
A7: =P!A1542 -> P2-BCMS | B7: =P!D1549 -> 472000 | C7: Propela Turbina 200 mm eje 1 1/4 " con Manzana Acero 316SS
A8: =P!A1578 -> P2-BEC | B8: =P!D1584 -> 450000 | C8: Propela Turbina 200 mm eje 2" con Casquete 304SS
A9: =P!A1586 -> P2-BECS | B9: =P!D1592 -> 561000 | C9: Propela Turbina 200 mm eje 2" con Casquete 316SS
A10: =P!A784 -> P2-BEM | B10: =P!D791 -> 519150 | C10: Propela Turbina 200 mm eje 2" con Manzana Acero 304SS
A11: =+P!A2161 -> P2-CCM | B11: =+P!D2168 -> 458100 | C11: Propela Turbina 300 mm eje 1 1/4" con Manzana Acero 304SS
A12: =P!A1534 -> P2-CGC | B12: =P!D1540 -> 660000 | C12: Propela Turbina 300 mm eje 3" con Casquete Acero 304SS
A13: =P!A11 -> P2-DBM | B13: =P!D18 -> 441250 | C13: Propela Turbina 350 mm eje 1" con Manzana Acero 304SS
A14: =P!A21 -> P2-DCM | B14: =P!D28 -> 473100 | C14: Propela Turbina 350 mm eje 1 1/4" con Manzana Acero 304SS
A15: =P!A1551 -> P2-DCMS | B15: =P!D1558 -> 525000 | C15: Propela Turbina 350 mm eje 1 1/4" con Manzana Acero 316SS
A16: =P!A567 -> P2-DDM | B16: =P!D574 -> 433100 | C16: Propela Turbina 350 mm eje 1 1/2" con Manzana Acero 304SS
A17: =P!A1497 -> P2-DDMS | B17: =P!D1504 -> 525000 | C17: Propela Turbina 350 mm eje 1 1/2" con Manzana Acero 316SS
A18: =P!A854 -> P2-DEM | B18: =P!D861 -> 569150 | C18: Propela Turbina 350 mm eje 2" con Manzana Acero 304SS
A19: =P!A1366 -> P2-GDM | B19: =P!D1373 -> 523100 | C19: Propela Turbina 500 mm eje 1 1/2" con Manzana Acero 304SS
A20: =P!A61 -> P2-GDMS | B20: =P!D68 -> 581000 | C20: Propela Turbina 500 mm eje 1 1/2" con Manzana Acero 316SS
A21: =P!A586 -> P2-GEM | B21: =P!D593 -> 619150 | C21: Propela Turbina 500 mm eje 2" con Manzana Acero 304SS
A22: =P!A766 -> P2-GEMS | B22: =P!D773 -> 664150 | C22: Propela Turbina 500 mm eje 2" con Manzana Acero 316SS
A23: =+P!A1882 -> P2-GFC | B23: =+P!D1888 -> 580000 | C23: Propela Turbina 500 mm eje 2 1/2" con Casquete Acero 304SS
A24: =P!A961 -> P2-GFM | B24: =P!D968 -> 649150 | C24: Propela Turbina 500 mm eje 2 1/2" con Manzana Acero 304SS
A25: =P!A667 -> P2-GGC | B25: =P!D673 -> 610000 | C25: Propela Turbina 500 mm eje 3" con Casquete Acero 304SS
A26: =P!A811 -> P2-GIC | B26: =P!D817 -> 640000 | C26: Propela Turbina 500 mm eje 4" con Casquete Acero 304SS
A27: =P!A31 -> P2-HCM | B27: =P!D38 -> 563465 | C27: Propela Turbina 550 mm eje 1 1/4" con Manzana Acero 304SS
A28: =P!A1132 -> P2-HDM | B28: =P!D1139 -> 679150 | C28: Propela Turbina 550 mm eje 1 1/2" con Manzana Acero 304SS
A29: =P!A1798 -> P2-HEC | B29: =P!D1804 -> 610000 | C29: Propela Turbina 550 mm eje 2" con Casquete Acero 304SS
A30: =P!A501 -> P2-HEM | B30: =P!D508 -> 679150 | C30: Propela Turbina 550 mm eje 2" con manzana Acero 304SS
A31: =P!A952 -> P2-HFM | B31: =P!D959 -> 679150 | C31: Propela Turbina 550 mm eje 2 1/2" con manzana Acero 304SS
A32: =P!A1349 -> P2-HFMS | B32: =P!D1356 -> 730150 | C32: Propela Turbina 550 mm eje 2 1/2" con manzana Acero 316SS
A33: =P!A997 -> P2-HGC | B33: =P!D1004 -> 750000 | C33: Propela Turbina 550 mm eje 3" con Casquete Acero 304SS
A34: =P!A1630 -> P2-JDM | B34: =P!D1637 -> 779150 | C34: Propela Turbina 700 mm eje 1 1/2" con Manzana Acero 304SS
A35: =P!A121 -> P2-JEM | B35: =P!D128 -> 779150 | C35: Propela Turbina 700 mm eje 2" con Manzana Acero 304SS
A36: =P!A1171 -> P2-JFC | B36: =P!D1177 -> 740000 | C36: Propela Turbina 700 mm eje 2 1/2" con Casquete Acero 304SS
A37: =P!A151 -> P2-JGC | B37: =P!D157 -> 770000 | C37: Propela Turbina 700 mm eje 3" con Casquete Acero 304SS
A38: =P!A1179 -> P2-JIC | B38: =P!D1185 -> 800000 | C38: Propela Turbina 700 mm eje 4" con Casquete Acero 304SS
A39: =P!A1323 -> P2-JICS | B39: =P!D1329 -> 889000 | C39: Propela Turbina 700 mm eje 4" con Casquete Acero 316SS
A40: =P!A131 -> P2-KDM | B40: =P!D138 -> 763100 | C40: Propela Turbina 800 mm eje 1 1/2" con Manzana Acero 304SS
A41: =+P!A2137 -> P2-KEC | B41: =+P!D2143 -> 790000 | C41: Propela Turbina 800 mm eje 2" con Casquete Acero 304SS
A42: =P!A141 -> P2-KEM | B42: =P!D148 -> 859150 | C42: Propela Turbina 800 mm eje 2" con Manzana Acero 304SS
A43: =P!A1516 -> P2-KFC | B43: =P!D1522 -> 820000 | C43: Propela Turbina 800 mm eje 2 1/2" con Casquete Acero 304SS
A44: =P!A160 -> P2-KGC | B44: =P!D166 -> 850000 | C44: Propela Turbina 800 mm eje 3" con Casquete Acero 304SS
A45: =P!A170 -> P2-KIC | B45: =P!D176 -> 880000 | C45: Propela Turbina 800 mm eje 4" con Casquete Acero 304SS
A46: =P!A749 -> P2-KJC | B46: =P!D755 -> 920000 | C46: Propela Turbina 800 mm eje 6" con Casquete Acero 304SS
A47: =P!A1358 -> P2-KJCS | B47: =P!D1364 -> 1028000 | C47: Propela Turbina 800 mm eje 6" con Casquete Acero 316SS
A48: =P!A1222 -> P2-KMC | B48: =P!D1228 -> 900000 | C48: Propela Turbina 800 mm eje 5" con Casquete Acero 304SS
A49: =+P!A2145 -> P2-LGC | B49: =+P!D2151 -> 1080000 | C49: Propela Turbina 1000 mm eje 3" con Casquete Acero 304SS
A50: =P!A1195 -> P2-LIC | B50: =P!D1201 -> 1110000 | C50: Propela Turbina 1000 mm eje 4" con Casquete Acero 304SS
A51: P2-LICS | B51: =+P!D2135 -> 1215000 | C51: Propela Turbina 1000 mm eje 4" con Casquete Acero 316SS
A52: =P!A1187 -> P2-LJC | B52: =P!D1193 -> 1150000 | C52: Propela Turbina 1000 mm eje 6" con Casquete Acero 304SS
A53: =P!A1665 -> P2-MGCS | B53: =P!D1671 -> 960000 | C53: Propela Turbina 1200 mm eje 3" con Casquete Acero 316SS
A54: =P!A1693 -> P2-MICS | B54: =P!D1699 -> 1270000 | C54: Propela Turbina 1200 mm eje 4" con Casquete Acero 316SS
A55: =P!A1305 -> P2-XDM | B55: =P!D1312 -> 923100 | C55: Propela Turbina 900 mm eje 1 1/2" con Manzana Acero 304SS
A56: =P!A1710 -> P2-XGC | B56: =P!D1716 -> 1010000 | C56: Propela Turbina 900 mm eje 3" con Casquete Acero 304SS
A57: =P!A1718 -> P2-XGCS | B57: =P!D1724 -> 1165000 | C57: Propela Turbina 900 mm eje 3" con Casquete Acero 316SS
A58: =P!A1239 -> P2-XMC | B58: =P!D1245 -> 1060000 | C58: Propela Turbina 900 mm eje 5" con Casquete Acero 304SS
A59: =P!A180 -> P3-BBM | B59: =P!D187 -> 436250 | C59: Propela Tripala 200 mm eje 1" con Manzana Acero 304SS
A60: =P!A1450 -> P3-BBMS | B60: =P!D1457 -> 482200 | C60: Propela Tripala 200 mm eje 1" con Manzana Acero 316SS
A61: =P!A926 -> P3-BCM | B61: =P!D933 -> 468100 | C61: Propela Tripala 200 mm eje 1 1/4" con Manzana Acero 304SS
A62: =P!A190 -> P3-CBM | B62: =P!D197 -> 451250 | C62: Propela Tripala 300 mm eje 1" con Manzana Acero 304SS
A63: =P!A454 -> P3-CBMS | B63: =P!D461 -> 501200 | C63: Propela Tripala 300 mm eje 1" con Manzana Acero 316SS
A64: =P!A91 -> P3-CCM | B64: =P!D98 -> 483100 | C64: Propela Tripala 300 mm eje 1 1/4" con Manzana Acero 304SS
A65: =P!A675 -> P3-CCMS | B65: =P!D682 -> 538000 | C65: Propela Tripala 300 mm eje 1 1/4" con Manzana Acero 316SS
A66: =P!A693 -> P3-CDM | B66: =P!D700 -> 483100 | C66: Propela Tripala 300 mm eje 1 1/2" con Manzana Acero 304SS
A67: =P!A1746 -> P3-CEC | B67: =P!D1752 -> 500000 | C67: Propela Tripala 300 mm eje 2" con Casquete Acero 304SS
A68: =P!A200 -> P3-EBM | B68: =P!D207 -> 476250 | C68: Propela Tripala 400 mm eje 1" con Manzana Acero 304SS
A69: =P!A445 -> P3-EBMS | B69: =P!D452 -> 532200 | C69: Propela Tripala 400 mm eje 1" con Manzana Acero 316SS
A70: =P!A613 -> P3-ECM | B70: =P!D620 -> 515800 | C70: Propela Tripala 400 mm eje 1 1/4" con Manzana Acero 304SS
A71: =P!A1613 -> P3-ECMS | B71: =P!D1620 -> 581000 | C71: Propela Tripala 400 mm eje 1 1/4" con Manzana Acero 316SS
A72: =P!A1639 -> P3-EDC | B72: =P!D1645 -> 515000 | C72: Propela Tripala 400 mm eje 1 1/2" con Casquete Acero 304SS
A73: =P!A111 -> P3-EDM | B73: =P!D118 -> 515800 | C73: Propela Tripala 400 mm eje 1 1/2" con Manzana Acero 304SS
A74: =P!A793 -> P3-EEC | B74: =P!D800 -> 605000 | C74: Propela Tripala 400 mm eje 2" con Casquete Acero 304SS
A75: =P!A979 -> P3-EEM | B75: =P!D986 -> 627200 | C75: Propela Tripala 400 mm eje 2" con Manzana Acero 304SS
A76: =P!A890 -> P3-EFC | B76: =P!D897 -> 625000 | C76: Propela Tripala 400 mm eje 2 1/2" con Casquete Acero 304SS
A77: =P!A881 -> P3-GBM | B77: =P!D888 -> 541250 | C77: Propela Tripala 500 mm eje 1" con Manzana Acero 304SS
A78: =P!A210 -> P3-GCM | B78: =P!D217 -> 573100 | C78: Propela Tripala 500 mm eje 1 1/4" con Manzana Acero 304SS
A79: =P!A2090 -> P3-GDC | B79: =P!D2097 -> 655000 | C79: Propela Tripala 500 mm eje 1 1/2" con casquete 304SS
A80: =P!A2099 -> P3-GDCS | B80: =P!D2106 -> 745000 | C80: Propela Tripala 500 mm eje 1 1/2" con casquete 316SS
A81: =P!A71 -> P3-GDM | B81: =P!D78 -> 573100 | C81: Propela Tripala 500 mm eje 1 1/2" con Manzana Acero 304SS
A82: =P!A81 -> P3-GDMS | B82: =P!D88 -> 646000 | C82: Propela Tripala 500 mm eje 1 1/2" con Manzana Acero 316SS
A83: =+P!A1945 -> P3-GEC | B83: =+P!D1952 -> 665000 | C83: Propela Tripala 500 mm eje 2" con Casquete Acero 304SS
A84: =+P!A2054 -> P3-GECS | B84: =+P!D2061 -> 745000 | C84: Propela Tripala 500 mm eje 2" con Casquete Acero 316SS
A85: =P!A775 -> P3-GEM | B85: =P!D782 -> 669150 | C85: Propela Tripala 500 mm eje 2" con Manzana Acero 304SS
A86: =P!A1441 -> P3-GEMS | B86: =P!D1448 -> 729150 | C86: Propela Tripala 500 mm eje 2" con Manzana Acero 316SS
A87: =P!A988 -> P3-GFM | B87: =P!D995 -> 669150 | C87: Propela Tripala 500 mm eje 2 1/2" con Manzana Acero 304SS
A88: =P!A1340 -> P3-GFMS | B88: =P!D1347 -> 729150 | C88: Propela Tripala 500 mm eje 2 1/2" con Manzana Acero 316SS
A89: =P!A1622 -> P3-GFC | B89: =P!D1628 -> 610000 | C89: Propela Tripala 500 mm eje 2 1/2" con Casquete Acero 304SS
A90: =+P!A1890 -> P3-GGC | B90: =+P!D1897 -> 705000 | C90: Propela Tripala 500 mm eje 3" con Casquete Acero 304SS
A91: =P!A1114 -> P3-GIC | B91: =P!D1121 -> 765000 | C91: Propela Tripala 500 mm eje 4" con Manzana Acero 304SS
A92: =P!A538 -> P3-IBM | B92: =P!D545 -> 663100 | C92: Propela Tripala 600 mm eje 1" con manzana Acero 304SS
A93: =P!A1314 -> P3-ICM | B93: =P!D1321 -> 663100 | C93: Propela Tripala 600 mm eje 1 1/4" con Manzana Acero 304SS
A94: =P!A547 -> P3-IDM | B94: =P!D554 -> 663100 | C94: Propela Tripala 600 mm eje 1 1/2" con manzana Acero 304SS
A95: =P!A1764 -> P3-IDMS | B95: =P!D1771 -> 748000 | C95: Propela Tripala 600 mm eje 1 1/2" con manzana Acero 316SS
A96: =+P!A2010 -> P3-IEC | B96: =+P!D2016 -> 680000 | C96: Propela Tripala 600 mm eje 2" con Casquete Acero 304SS
A97: =P!A220 -> P3-IEM | B97: =P!D227 -> 759150 | C97: Propela Tripala 600 mm eje 2" con Manzana Acero 304SS
A98: =+P!A1994 -> P3-IFC | B98: =+P!D2000 -> 700000 | C98: Propela Tripala 600 mm eje 2 1/2" con Casquete Acero 304SS
A99: =+P!A2002 -> P3-IFCS | B99: =+P!D2008 -> 792000 | C99: Propela Tripala 600 mm eje 2 1/2" con Casquete Acero 316SS
A100: =P!A970 -> P3-IFM | B100: =P!D977 -> 759150 | C100: Propela Tripala 600 mm eje 2 1/2" con Manzana Acero 304SS
...

Sheet HERR CODS
A1: EJE | C1: ACOPLE | E1: SCHEDULE | G1: LONGITUD | I1: DIÁMETRO NOMINAL | K1: MATERIAL
C2: BRIDADO | D2: B | E2: MACIZO | F2: A | G2: XXX | I2: (3/4") | J2: A | K2: Acero A36 | L2: R
C3: DIRECTO | D3: D | E3: SCH 10 | F3: B | G3: cm | I3: (1") | J3: B | K3: Acero 316SS | L3: S
E4: SCH 40 | F4: C | I4: (1.1/4") | J4: C | K4: Acero 304SS
E5: SCH 80 | F5: D | I5: (1.1/2") | J5: D
I6: (2") | J6: E
I7: (2.1/2") | J7: F
I8: (3") | J8: G
I9: (3.1/2") | J9: H
E10: EJES | I10: (4") | J10: I
I11: (5") | J11: M
I12: (6") | J12: J
I13: (8") | J13: K
I14: (10") | J14: L
A15: AB | B15: - | C15: 2.5 | D15: - | E15: 035 | F15: - | G15: S
B18: ACOPLE BRIDADO | F18: Casillas Opcionales. Sólo serán tenidas en cuenta
F19: para una selección de material NO estándar.
A20: ACOPLE | B20: - | C20: DIAMETRO | E20: DIAMETRO | G20: MATERIAL
C21: NOMINAL | D21: - | E21: EJE | F21: -
A22: BRIDADO | C22: BRIDA | E22: MOTOREDUCTOR
C23: Hasta tres cifras. En pulgadas. | E23: Tres cifras en mm | G23: P | H23: ACERO AL CARBON PAVONADO
B24: 2" | C24: 2 | E24: 14 | F24: 014 | G24: S | H24: 316SS
B25: 2 1/2" | C25: 2.5 | E25: 18 | F25: 018 | G25: R | H25: ACERO AL CARBON
B26: 3" | C26: 3 | E26: 20 | F26: 020 | G26: Q | H26: RECUBRIMIENTO EN FIBRA DE VIDRIO | P26: 20 | Q26: 20
B27: 4" | C27: 4 | E27: 25 | F27: 025 | P27: 25 | Q27: 25
B28: 6" | C28: 6 | E28: 30 | F28: 030 | P28: 30 | Q28: 30
B29: 8" | C29: 8 | E29: 35 | F29: 035 | P29: 35 | Q29: 35
E30: 40 | F30: 040 | P30: 40 | Q30: 40
E31: 50 | F31: 050 | P31: 50 | Q31: 50
E32: 60 | F32: 060 | P32: 60 | Q32: 60
E33: 70 | F33: 070 | P33: 70 | Q33: 70
E34: 80 | F34: 080 | P34: 80 | Q34: 80
E35: 90 | F35: 090 | P35: 90 | Q35: 90
E36: 100 | F36: 100 | K36: Casilla opcional. Sólo será tenida en cuenta | P36: 100 | Q36: 100
K38: para una selección de material NO estándar.
A39: TIPO | C39: - | D39: DIÁMETRO DE PROPELA | G39: DIÁMETRO NOMINAL EJE | I39: MONTAJE | K39: MATERIAL
A40: HIPERBOLICA | B40: 1 | D40: 160 | E40: A | F40: cm | G40: (3/4") | H40: A | I40: MANZANA | J40: M | L40: A36 | M40: Acero A36 | N40: R
A41: TURBINA | B41: 2 | D41: 200 | E41: B | F41: cm | G41: (1") | H41: B | I41: CASQUETE | J41: C | L41: S6 | M41: Acero inoxidable 316SS | N41: S
A42: CURVA TRIPALA - CT | B42: 3 | D42: 300 | E42: C | F42: cm | G42: (1.1/4") | H42: C | I42: SOLDADA | J42: S | M42: Acero inoxidable 304SS
A43: GRAN CAUDAL - GC | B43: 4 | D43: 350 | E43: D | F43: cm | G43: (1.1/2") | H43: D
A44: BIPALA - CB | B44: 5 | D44: 400 | E44: E | F44: cm | G44: (2") | H44: E
A45: CURVA TRIPALA ESQUALIZABLE - CTE | B45: 6 | D45: 420 | E45: F | F45: cm | G45: (2.1/2") | H45: F
A46: TURBINA TRIPALA - TT | B46: 7 | D46: 500 | E46: G | F46: cm | G46: (3") | H46: G
A47: CURVA TRIPALA COMBINADA - CTT | B47: 8 | D47: 550 | E47: H | F47: cm | G47: (3.1/2") | H47: H
A48: COWLES - CW | B48: 9 | D48: 600 | E48: I | F48: cm | G48: (4") | H48: I
A49: GRAN CAUDAL ESCUALIZABLE - GCE | B49: 0 | D49: 700 | E49: J | F49: cm | G49: (5") | H49: M
D50: 800 | E50: K | F50: cm | G50: (6") | H50: J
D51: 900 | E51: X | F51: cm | G51: (8") | H51: K
D52: 1000 | E52: L | F52: cm | G52: (10") | H52: L
D53: 3600 | E53: T | F53: cm
D54: 1200 | E54: M | F54: cm
D55: 1500 | E55: N | F55: cm
D56: 1800 | E56: O | F56: cm
D57: 1900 | E57: P | F57: cm
D58: 2500 | E58: U | F58: cm
D59: 2000 | E59: Q | F59: cm
D60: 1400 | E60: R | F60: cm
D61: 1600 | E61: S | F61: cm
D62: 750 | E62: W | F62: cm
D63: 3000 | E63: V | F63: cm
D64: 2200 | E64: Z | F64: cm
F66: Casillas Opcionales. Sólo serán tenidas en cuenta
A67: ACOPLE | B67: - | C67: DIAMETRO | F67: para una selección de material NO estándar. | G67: MATERIAL
C68: EJE | E68: DIAMETRO
A69: DIRECTO | C69: MOTOREDUCTOR | D69: - | E69: NOMINAL | F69: -
C70: Tres cifras en mm | E70: EJE | G70: P | H70: ACERO AL CARBON PAVONADO | I70: -P
E71: Tres cifras en mm | G71: S | H71: 316SS | I71: -S
B72: 1" | C72: 025 | G72: R | H72: ACERO AL CARBON | I72: -R
B73: 1 1/4" | C73: 032 | G73: Q | H73: RECUBRIMIENTO EN FIBRA DE VIDRIO | I73: -Q
B74: 1 1/2" | C74: 038 | H74: ACERO 304SS
B75: 2" | C75: 050
A79: MONTAJE | C79: TIPO DE PROPELA | G79: DIAMETRO | I79: TIPO DE PROPELA | K79: N DE PROPELAS | M79: DIAMETRO | O79: LONGITUD EJE | Q79: POTENCIA (kW) | S79: VELOCIDAD | U79: TIPO DE AGITADOR | W79: ELEMENTO MOTRIZ | Y79: LINTERNA | AA79: SELLO MECANICO | AC79: MATERIAL
E80: N DE PROPELAS
A81: V | B81: VERTICAL | C81: 1 | D81: HELICE MARINA | G81: A | H81: 160 | I81: 1 | J81: HELICE MARINA | K81: A | L81: 1 | M81: A | N81: 160 mm | O81: XX en DECIMETROS | Q81: A | R81: 0.25 | S81: xxx | T81: RPM | U81: D | V81: VELOCIDAD DIRECTA | W81: N | X81: MOTOR NEUMATICO | Y81: L | Z81: Con linterna | AA81: W | AB81: Con sello | AC81: S | AD81: 316SS
A82: H | B82: HORIZONTAL | C82: 2 | D82: TURBINA | E82: A | F82: 1 | G82: B | H82: 200 | I82: 2 | J82: TURBINA | K82: B | L82: 2 | M82: B | N82: 200 | Q82: B | R82: 0.37 | W82: X | X82: MOTOR ELECTRICO A PRUEBA DE EXPLOSIÓN | AC82: R | AD82: ACERO AL CARBON
A83: VERTICAL | B83: V | C83: 3 | D83: CURVA TRIPALA - CT | E83: B | F83: 2 | G83: C | H83: 300 | I83: 3 | J83: CURVA TRIPALA - CT | K83: C | L83: 3 | M83: C | N83: 300 | Q83: C | R83: 0.55 | W83: V | X83: 110V (REVISAR) | AC83: Q | AD83: RECUBRIMIENTO EN FIBRA DE VIDRIO
A84: HORIZONTAL | B84: H | C84: 4 | D84: GRAN CAUDAL - GC | E84: C | F84: 3 | G84: D | H84: 350 | I84: 4 | J84: GRAN CAUDAL - GC | K84: D | L84: 4 | M84: D | N84: 350 | Q84: D | R84: 0.75
C85: 5 | D85: BIPALA - CB | E85: D | F85: 4 | G85: E | H85: 400 | I85: 5 | J85: BIPALA - CB | M85: E | N85: 400 | Q85: E | R85: 1.1 | AC85: E | AD85: PINTURA EPOXICA
C86: 6 | D86: CURVA TRIPALA ESQUALIZABLE - CE | G86: F | H86: 500 | I86: 6 | J86: ESQUALIZABLE - CE | M86: F | N86: 500 | Q86: F | R86: 1.5
C87: 7 | D87: TURBINA TRIPALA - TT | G87: G | H87: 550 | I87: 7 | J87: TURBINA TRIPALA - TT | M87: G | N87: 550 | Q87: G | R87: 2.2 | AC87: T | AD87: 904 L
C88: 8 | D88: CURVA TRIPALA COMBINADA - CTT | G88: H | H88: 600 | I88: 8 | J88: CURVA TRIPALA COMBINADA - CTT | M88: H | N88: 600 | Q88: H | R88: 3
C89: 9 | D89: COWLES - CW | G89: I | H89: 700 | I89: 9 | J89: COWLES - CW | M89: I | N89: 700 | Q89: I | R89: 4 | AE89: ACERO 316L SCH10 | AF89: U
C90: 0 | D90: ITC POLIPROPILENO | G90: J | H90: 800 | M90: J | N90: 800 | Q90: J | R90: 5.5 | U90: VELOCIDAD DIRECTA | V90: D | W90: MOTOR NEUMATICO | X90: N | Y90: Con linterna | Z90: L | AA90: Con sello | AB90: W | AC90: 316SS | AD90: S | AE90: PINTURA EPOXICA | AF90: E
C91: HIPERBOLICA | D91: 1 | G91: K | H91: 1000 | M91: K | N91: 1000 | Q91: K | R91: 7.5 | U91: VELOCIDAD REDUCIDA | W91: MOTOR ELECTRICO A PRUEBA DE EXPLOSIÓN | X91: X | Y91: Sin linterna | AA91: Sin sello | AC91: ACERO AL CARBON | AD91: R | AE91: FIBRA DE VIDRIO | AF91: Q
C92: TURBINA | D92: 2 | E92: 1 | F92: A | G92: L | H92: 1200 | I92: HELICE MARINA | J92: 1 | M92: L | N92: 1200 | Q92: M | R92: 9.2 | W92: INVERT DUTY | X92: I | AC92: 904L | AD92: T | AE92: POLIPROPILENO | AF92: Y
C93: CURVA TRIPALA - CT | D93: 3 | E93: 2 | F93: B | G93: M | H93: 1500 | I93: TURBINA | J93: 2 | M93: M | N93: 1500 | Q93: N | R93: 11 | W93: 110V (REVISAR) | X93: V | AC93: 304SS | AE93: POLIETILENO | AF93: P
C94: GRAN CAUDAL - GC | D94: 4 | E94: 3 | F94: C | G94: N | H94: 1600 | I94: CURVA TRIPALA - CT | J94: 3 | M94: N | N94: 1600 | Q94: O | R94: 15 | W94: WASH DOWN | X94: Z | AE94: ACABADO ESPEJO | AF94: M
C95: BIPALA - CB | D95: 5 | E95: 4 | F95: D | G95: O | H95: 1800 | I95: GRAN CAUDAL - GC | J95: 4 | M95: O | N95: 1800 | Q95: P | R95: 18.5 | W95: TRIFASICO | AE95: NINGUNO
C96: CURVA TRIPALA ESQUALIZABLE - CE | D96: 6 | E96: NO APLICA | G96: P | H96: 2000 | I96: BIPALA - CB | J96: 5 | M96: P | N96: 2000 | Q96: Q | R96: 22
C97: TURBINA TRIPALA - TT | D97: 7 | G97: Q | H97: 2500 | I97: ESQUALIZABLE - CE | J97: 6 | M97: Q | N97: 2500 | Q97: R | R97: 30
C98: CURVA TRIPALA COMBINADA - CTT | D98: 8 | G98: R | H98: 60 | I98: TURBINA TRIPALA - TT | J98: 7 | Q98: S | R98: 37
C99: COWLES - CW | D99: 9 | G99: S | H99: 90 | I99: CURVA TRIPALA COMBINADA - CTT | J99: 8 | Q99: T | R99: 0.08
C100: ITC POLIPROPILENO | D100: 0 | G100: T | H100: 120 | I100: COWLES - CW | J100: 9 | Q100: U | R100: 0.185
C101: NO APLICA | I101: ITC POLIPROPILENO | J101: 0 | Q101: V | R101: 0.18 | AC101: 316SS | AD101: S
G102: 160 | H102: A | AC102: ACERO AL CARBON | AD102: R
G103: 200 | H103: B | Q103: 0.25 | R103: A | AC103: 904L | AD103: T
G104: 300 | H104: C | Q104: 0.37 | R104: B | AC104: 304SS
G105: 350 | H105: D | Q105: 0.55 | R105: C
G106: 400 | H106: E | Q106: 0.75 | R106: D
G107: 500 | H107: F | Q107: 1.1 | R107: E
...

Sheet RESUMEN (2)
E3: AGITADORES TIPO TURBINA
C4: DESCRIPCION DEL EQUIPO | D4: AGITADOR | H4: MOTOR | K4: DESCRIPCION DEL EQUIPO
B5: MODELO | D5: Diam prop (mm) | E5: Long Max | F5: Peso aprox (kg) | G5: DIMENSIONES EMBALAJE (mm) | H5: POTENCIA (kW) | I5: RPM
B6: V2AB-06A137 | C6: Agitador Vertical, Propela Tipo Turbina de 200 mm de Diámetro, Longitud Maxima de Eje: 640 mm, Potencia del Motoreductor: 0,25 kW | D6: 200 | E6: 640 | F6: =L6*2 -> 42 | G6: 700*350*300 | H6: 0.25 | I6: 137 | K6: =CONCATENATE("Agitador Vertical, Propela Tipo Turbina de ",D6," mm de Diámetro, Longitud Maxima de Eje: ",E6, " mm, Potencia del Motoreductor: ",H6, " kW") -> Agitador Vertical, Propela Tipo Turbina de 200 mm de Diámetro, Longitud Maxima de Eje: 640 mm, Potencia del Motoreductor: 0,25 kW | L6: 21
B7: V2AD-09A137 | C7: Agitador Vertical, Propela Tipo Turbina de 350 mm de Diámetro, Longitud Maxima de Eje: 900 mm, Potencia del Motoreductor: 0,25 kW | D7: 350 | E7: 900 | F7: =L7*2 -> 48 | G7: 1000*450*400 | H7: 0.25 | I7: 137 | K7: =CONCATENATE("Agitador Vertical, Propela Tipo Turbina de ",D7," mm de Diámetro, Longitud Maxima de Eje: ",E7, " mm, Potencia del Motoreductor: ",H7, " kW") -> Agitador Vertical, Propela Tipo Turbina de 350 mm de Diámetro, Longitud Maxima de Eje: 900 mm, Potencia del Motoreductor: 0,25 kW | L7: 24
B8: V2AD-11C192 | C8: Agitador Vertical, Propela Tipo Turbina de 350 mm de Diámetro, Longitud Maxima de Eje: 1090 mm, Potencia del Motoreductor: 0,55 kW | D8: 350 | E8: 1090 | F8: =L8*2 -> 66 | G8: 1200*450*400 | H8: 0.55 | I8: 192 | K8: =CONCATENATE("Agitador Vertical, Propela Tipo Turbina de ",D8," mm de Diámetro, Longitud Maxima de Eje: ",E8, " mm, Potencia del Motoreductor: ",H8, " kW") -> Agitador Vertical, Propela Tipo Turbina de 350 mm de Diámetro, Longitud Maxima de Eje: 1090 mm, Potencia del Motoreductor: 0,55 kW | L8: 33
B9: V2AG-14C086 | C9: Agitador Vertical, Propela Tipo Turbina de 550 mm de Diámetro, Longitud Maxima de Eje: 1450 mm, Potencia del Motoreductor: 0,55 kW | D9: 550 | E9: 1450 | F9: =L9*2 -> 120 | G9: 1600*600*500 | H9: 0.55 | I9: 86 | K9: =CONCATENATE("Agitador Vertical, Propela Tipo Turbina de ",D9," mm de Diámetro, Longitud Maxima de Eje: ",E9, " mm, Potencia del Motoreductor: ",H9, " kW") -> Agitador Vertical, Propela Tipo Turbina de 550 mm de Diámetro, Longitud Maxima de Eje: 1450 mm, Potencia del Motoreductor: 0,55 kW | L9: 60
B10: V2AI-16E072 | C10: Agitador Vertical, Propela Tipo Turbina de 700 mm de Diámetro, Longitud Maxima de Eje: 1600 mm, Potencia del Motoreductor: 1,1 kW | D10: 700 | E10: 1600 | F10: =L10*2 -> 182 | G10: 1700*600*500 | H10: 1.1 | I10: 72 | K10: =CONCATENATE("Agitador Vertical, Propela Tipo Turbina de ",D10," mm de Diámetro, Longitud Maxima de Eje: ",E10, " mm, Potencia del Motoreductor: ",H10, " kW") -> Agitador Vertical, Propela Tipo Turbina de 700 mm de Diámetro, Longitud Maxima de Eje: 1600 mm, Potencia del Motoreductor: 1,1 kW | L10: 91
B11: V2AI-18F077 | C11: Agitador Vertical, Propela Tipo Turbina de 700 mm de Diámetro, Longitud Maxima de Eje: 1800 mm, Potencia del Motoreductor: 1,5 kW | D11: 700 | E11: 1800 | F11: =L11*1.5 -> 141 | G11: 1900*600*500 | H11: 1.5 | I11: 77 | K11: =CONCATENATE("Agitador Vertical, Propela Tipo Turbina de ",D11," mm de Diámetro, Longitud Maxima de Eje: ",E11, " mm, Potencia del Motoreductor: ",H11, " kW") -> Agitador Vertical, Propela Tipo Turbina de 700 mm de Diámetro, Longitud Maxima de Eje: 1800 mm, Potencia del Motoreductor: 1,5 kW | L11: 94
B12: V2AJ-20B046 | C12: Agitador Vertical, Propela Tipo Turbina de 800 mm de Diámetro, Longitud Maxima de Eje: 2000 mm, Potencia del Motoreductor: 0,37 kW | D12: 800 | E12: 2000 | F12: =L12*1.5 -> 124.5 | G12: 2105*700*600 | H12: 0.37 | I12: 46 | K12: =CONCATENATE("Agitador Vertical, Propela Tipo Turbina de ",D12," mm de Diámetro, Longitud Maxima de Eje: ",E12, " mm, Potencia del Motoreductor: ",H12, " kW") -> Agitador Vertical, Propela Tipo Turbina de 800 mm de Diámetro, Longitud Maxima de Eje: 2000 mm, Potencia del Motoreductor: 0,37 kW | L12: 83
B13: V2AJ-21E063 | C13: Agitador Vertical, Propela Tipo Turbina de 800 mm de Diámetro, Longitud Maxima de Eje: 2100 mm, Potencia del Motoreductor: 1,1 kW | D13: 800 | E13: 2100 | F13: =L13*1.5 -> 159 | G13: 2200*700*600 | H13: 1.1 | I13: 63 | K13: =CONCATENATE("Agitador Vertical, Propela Tipo Turbina de ",D13," mm de Diámetro, Longitud Maxima de Eje: ",E13, " mm, Potencia del Motoreductor: ",H13, " kW") -> Agitador Vertical, Propela Tipo Turbina de 800 mm de Diámetro, Longitud Maxima de Eje: 2100 mm, Potencia del Motoreductor: 1,1 kW | L13: 106
B14: V2AI-24H108 | C14: Agitador Vertical, Propela Tipo Turbina de 700 mm de Diámetro, Longitud Maxima de Eje: 2400 mm, Potencia del Motoreductor: 3 kW | D14: 700 | E14: 2400 | F14: =L14*1.5 -> 243 | G14: 2500*700*600 | H14: 3 | I14: 108 | K14: =CONCATENATE("Agitador Vertical, Propela Tipo Turbina de ",D14," mm de Diámetro, Longitud Maxima de Eje: ",E14, " mm, Potencia del Motoreductor: ",H14, " kW") -> Agitador Vertical, Propela Tipo Turbina de 700 mm de Diámetro, Longitud Maxima de Eje: 2400 mm, Potencia del Motoreductor: 3 kW | L14: 162
B15: V2AJ-24H088 | C15: Agitador Vertical, Propela Tipo Turbina de 800 mm de Diámetro, Longitud Maxima de Eje: 2460 mm, Potencia del Motoreductor: 3 kW | D15: 800 | E15: 2460 | F15: =L15*1.5 -> 255 | G15: 2550*700*600 | H15: 3 | I15: 88 | K15: =CONCATENATE("Agitador Vertical, Propela Tipo Turbina de ",D15," mm de Diámetro, Longitud Maxima de Eje: ",E15, " mm, Potencia del Motoreductor: ",H15, " kW") -> Agitador Vertical, Propela Tipo Turbina de 800 mm de Diámetro, Longitud Maxima de Eje: 2460 mm, Potencia del Motoreductor: 3 kW | L15: 170
B16: V2AJ-26J102 | C16: Agitador Vertical, Propela Tipo Turbina de 800 mm de Diámetro, Longitud Maxima de Eje: 2660 mm, Potencia del Motoreductor: 5,5 kW | D16: 800 | E16: 2660 | F16: =L16*1.5 -> 318 | G16: 2710*700*600 | H16: 5.5 | I16: 102 | K16: =CONCATENATE("Agitador Vertical, Propela Tipo Turbina de ",D16," mm de Diámetro, Longitud Maxima de Eje: ",E16, " mm, Potencia del Motoreductor: ",H16, " kW") -> Agitador Vertical, Propela Tipo Turbina de 800 mm de Diámetro, Longitud Maxima de Eje: 2660 mm, Potencia del Motoreductor: 5,5 kW | L16: 212
E19: AGITADORES TIPO GRAN CAUDAL
C20: DESCRIPCION DEL EQUIPO | D20: AGITADOR | H20: MOTOR
B21: MODELO | D21: DIAMETRO PROPELA (mm) | E21: LONG MAX EJE (mm) | F21: PESO APROXIMADO (kg) | G21: DIMENSIONES EMBALAJE (mm) | H21: POTENCIA (kW) | I21: RPM | L21: PESO APROXIMADO (kg)
B22: V4AE-09B107 | C22: Agitador Vertical, Propela Tipo Gran Caudal de 400 mm de Diámetro, Longitud Maxima de Eje: 900 mm, Potencia del Motoreductor: 0,37 kW | D22: 400 | E22: 900 | F22: =L22*2 -> 64 | G22: 1000*500*450 | H22: 0.37 | I22: 107 | K22: =CONCATENATE("Agitador Vertical, Propela Tipo Gran Caudal de ",D22," mm de Diámetro, Longitud Maxima de Eje: ",E22, " mm, Potencia del Motoreductor: ",H22, " kW") -> Agitador Vertical, Propela Tipo Gran Caudal de 400 mm de Diámetro, Longitud Maxima de Eje: 900 mm, Potencia del Motoreductor: 0,37 kW | L22: 32
B23: V4AH-15E074 | C23: Agitador Vertical, Propela Tipo Gran Caudal de 600 mm de Diámetro, Longitud Maxima de Eje: 1520 mm, Potencia del Motoreductor: 1,1 kW | D23: 600 | E23: 1520 | F23: =L23*1.5 -> 160.5 | G23: 1600*600*500 | H23: 1.1 | I23: 74 | K23: =CONCATENATE("Agitador Vertical, Propela Tipo Gran Caudal de ",D23," mm de Diámetro, Longitud Maxima de Eje: ",E23, " mm, Potencia del Motoreductor: ",H23, " kW") -> Agitador Vertical, Propela Tipo Gran Caudal de 600 mm de Diámetro, Longitud Maxima de Eje: 1520 mm, Potencia del Motoreductor: 1,1 kW | L23: 107
B24: V4AJ-21E065 | C24: Agitador Vertical, Propela Tipo Gran Caudal de 800 mm de Diámetro, Longitud Maxima de Eje: 2160 mm, Potencia del Motoreductor: 1,1 kW | D24: 800 | E24: 2160 | F24: =L24*1.5 -> 204 | G24: 2200*700*600 | H24: 1.1 | I24: 65 | K24: =CONCATENATE("Agitador Vertical, Propela Tipo Gran Caudal de ",D24," mm de Diámetro, Longitud Maxima de Eje: ",E24, " mm, Potencia del Motoreductor: ",H24, " kW") -> Agitador Vertical, Propela Tipo Gran Caudal de 800 mm de Diámetro, Longitud Maxima de Eje: 2160 mm, Potencia del Motoreductor: 1,1 kW | L24: 136
B25: V4AK-27G053 | C25: Agitador Vertical, Propela Tipo Gran Caudal de 1000 mm de Diámetro, Longitud Maxima de Eje: 2700 mm, Potencia del Motoreductor: 2,2 kW | D25: 1000 | E25: 2700 | F25: =L25*1.5 -> 355.5 | G25: 2900*800*700 | H25: 2.2 | I25: 53 | K25: =CONCATENATE("Agitador Vertical, Propela Tipo Gran Caudal de ",D25," mm de Diámetro, Longitud Maxima de Eje: ",E25, " mm, Potencia del Motoreductor: ",H25, " kW") -> Agitador Vertical, Propela Tipo Gran Caudal de 1000 mm de Diámetro, Longitud Maxima de Eje: 2700 mm, Potencia del Motoreductor: 2,2 kW | L25: 237
B26: V4AL-27AH043 | C26: Agitador Vertical, Propela Tipo Gran Caudal de 1200 mm de Diámetro, Longitud Maxima de Eje: 2700 mm, Potencia del Motoreductor: 3 kW | D26: 1200 | E26: 2700 | F26: =L26*1.5 -> 475.5 | G26: 2900*800*700 | H26: 3 | I26: 43 | K26: =CONCATENATE("Agitador Vertical, Propela Tipo Gran Caudal de ",D26," mm de Diámetro, Longitud Maxima de Eje: ",E26, " mm, Potencia del Motoreductor: ",H26, " kW") -> Agitador Vertical, Propela Tipo Gran Caudal de 1200 mm de Diámetro, Longitud Maxima de Eje: 2700 mm, Potencia del Motoreductor: 3 kW | L26: 317
B27: V4AV-27AH033 | C27: Agitador Vertical, Propela Tipo Gran Caudal de 1400 mm de Diámetro, Longitud Maxima de Eje: 2700 mm, Potencia del Motoreductor: 3 kW | D27: 1400 | E27: 2700 | F27: =L27*1.5 -> 505.5 | G27: 2900*800*700 | H27: 3 | I27: 33 | K27: =CONCATENATE("Agitador Vertical, Propela Tipo Gran Caudal de ",D27," mm de Diámetro, Longitud Maxima de Eje: ",E27, " mm, Potencia del Motoreductor: ",H27, " kW") -> Agitador Vertical, Propela Tipo Gran Caudal de 1400 mm de Diámetro, Longitud Maxima de Eje: 2700 mm, Potencia del Motoreductor: 3 kW | L27: 337
E30: AGITADORES TIPO CURVA TRIPALA
C31: DESCRIPCION DEL EQUIPO | D31: AGITADOR | H31: MOTOR
B32: MODELO | D32: DIAMETRO PROPELA (mm) | E32: LONG MAX EJE (mm) | F32: PESO APROXIMADO (kg) | G32: DIMENSIONES EMBALAJE (mm) | H32: POTENCIA (kW) | I32: RPM
B33: V3AB-06B293 | C33: Agitador Vertical, Propela Tipo Curva Tripala de 200 mm de Diámetro, Longitud Maxima de Eje: 590 mm, Potencia del Motoreductor: 0,37 kW | D33: 200 | E33: 590 | F33: =L33*2 -> 42 | G33: 650*350*350 | H33: 0.37 | I33: 293 | K33: =CONCATENATE("Agitador Vertical, Propela Tipo Curva Tripala de ",D33," mm de Diámetro, Longitud Maxima de Eje: ",E33, " mm, Potencia del Motoreductor: ",H33, " kW") -> Agitador Vertical, Propela Tipo Curva Tripala de 200 mm de Diámetro, Longitud Maxima de Eje: 590 mm, Potencia del Motoreductor: 0,37 kW | L33: 21
B34: V3AC-09A189 | C34: Agitador Vertical, Propela Tipo Curva Tripala de 300 mm de Diámetro, Longitud Maxima de Eje: 860 mm, Potencia del Motoreductor: 0,25 kW | D34: 300 | E34: 860 | F34: =L34*2 -> 46 | G34: 900*400*400 | H34: 0.25 | I34: 189 | K34: =CONCATENATE("Agitador Vertical, Propela Tipo Curva Tripala de ",D34," mm de Diámetro, Longitud Maxima de Eje: ",E34, " mm, Potencia del Motoreductor: ",H34, " kW") -> Agitador Vertical, Propela Tipo Curva Tripala de 300 mm de Diámetro, Longitud Maxima de Eje: 860 mm, Potencia del Motoreductor: 0,25 kW | L34: 23
B35: V3AE-11B120 | C35: Agitador Vertical, Propela Tipo Curva Tripala de 400 mm de Diámetro, Longitud Maxima de Eje: 1080 mm, Potencia del Motoreductor: 0,37 kW | D35: 400 | E35: 1080 | F35: =L35*2 -> 50 | G35: 1150*500*400 | H35: 0.37 | I35: 120 | K35: =CONCATENATE("Agitador Vertical, Propela Tipo Curva Tripala de ",D35," mm de Diámetro, Longitud Maxima de Eje: ",E35, " mm, Potencia del Motoreductor: ",H35, " kW") -> Agitador Vertical, Propela Tipo Curva Tripala de 400 mm de Diámetro, Longitud Maxima de Eje: 1080 mm, Potencia del Motoreductor: 0,37 kW | L35: 25
B36: V3AF-13D129 | C36: Agitador Vertical, Propela Tipo Curva Tripala de 500 mm de Diámetro, Longitud Maxima de Eje: 1350 mm, Potencia del Motoreductor: 0,75 kW | D36: 500 | E36: 1350 | F36: =L36*2 -> 90 | G36: 1400*500*400 | H36: 0.75 | I36: 129 | K36: =CONCATENATE("Agitador Vertical, Propela Tipo Curva Tripala de ",D36," mm de Diámetro, Longitud Maxima de Eje: ",E36, " mm, Potencia del Motoreductor: ",H36, " kW") -> Agitador Vertical, Propela Tipo Curva Tripala de 500 mm de Diámetro, Longitud Maxima de Eje: 1350 mm, Potencia del Motoreductor: 0,75 kW | L36: 45
B37: V3AH-16G118 | C37: Agitador Vertical, Propela Tipo Curva Tripala de 600 mm de Diámetro, Longitud Maxima de Eje: 1620 mm, Potencia del Motoreductor: 2,2 kW | D37: 600 | E37: 1620 | F37: =L37*1.5 -> 141 | G37: 1700*600*500 | H37: 2.2 | I37: 118 | K37: =CONCATENATE("Agitador Vertical, Propela Tipo Curva Tripala de ",D37," mm de Diámetro, Longitud Maxima de Eje: ",E37, " mm, Potencia del Motoreductor: ",H37, " kW") -> Agitador Vertical, Propela Tipo Curva Tripala de 600 mm de Diámetro, Longitud Maxima de Eje: 1620 mm, Potencia del Motoreductor: 2,2 kW | L37: 94
B38: V3AI-18F089 | C38: Agitador Vertical, Propela Tipo Curva Tripala de 700 mm de Diámetro, Longitud Maxima de Eje: 1840 mm, Potencia del Motoreductor: 1,5 kW | D38: 700 | E38: 1840 | F38: =L38*1.5 -> 151.5 | G38: 1900*700*600 | H38: 1.5 | I38: 89 | K38: =CONCATENATE("Agitador Vertical, Propela Tipo Curva Tripala de ",D38," mm de Diámetro, Longitud Maxima de Eje: ",E38, " mm, Potencia del Motoreductor: ",H38, " kW") -> Agitador Vertical, Propela Tipo Curva Tripala de 700 mm de Diámetro, Longitud Maxima de Eje: 1840 mm, Potencia del Motoreductor: 1,5 kW | L38: 101
B39: V3AJ-20F159 | C39: Agitador Vertical, Propela Tipo Curva Tripala de 800 mm de Diámetro, Longitud Maxima de Eje: 2060 mm, Potencia del Motoreductor: 1,5 kW | D39: 800 | E39: 2060 | F39: =L39*1.5 -> 129 | G39: 2105*700*600 | H39: 1.5 | I39: 159 | K39: =CONCATENATE("Agitador Vertical, Propela Tipo Curva Tripala de ",D39," mm de Diámetro, Longitud Maxima de Eje: ",E39, " mm, Potencia del Motoreductor: ",H39, " kW") -> Agitador Vertical, Propela Tipo Curva Tripala de 800 mm de Diámetro, Longitud Maxima de Eje: 2060 mm, Potencia del Motoreductor: 1,5 kW | L39: 86
B40: V3AK-26G118 | C40: Agitador Vertical, Propela Tipo Curva Tripala de 1000 mm de Diámetro, Longitud Maxima de Eje: 2600 mm, Potencia del Motoreductor: 2,2 kW | D40: 1000 | E40: 2600 | F40: =L40*1.5 -> 193.5 | G40: 2700*900*750 | H40: 2.2 | I40: 118 | K40: =CONCATENATE("Agitador Vertical, Propela Tipo Curva Tripala de ",D40," mm de Diámetro, Longitud Maxima de Eje: ",E40, " mm, Potencia del Motoreductor: ",H40, " kW") -> Agitador Vertical, Propela Tipo Curva Tripala de 1000 mm de Diámetro, Longitud Maxima de Eje: 2600 mm, Potencia del Motoreductor: 2,2 kW | L40: 129
B41: V3AK-26H095 | C41: Agitador Vertical, Propela Tipo Curva Tripala de 1200 mm de Diámetro, Longitud Maxima de Eje: 2640 mm, Potencia del Motoreductor: 3 kW | D41: 1200 | E41: 2640 | F41: =L41*1.5 -> 250.5 | G41: 2750*1100*850 | H41: 3 | I41: 95 | K41: =CONCATENATE("Agitador Vertical, Propela Tipo Curva Tripala de ",D41," mm de Diámetro, Longitud Maxima de Eje: ",E41, " mm, Potencia del Motoreductor: ",H41, " kW") -> Agitador Vertical, Propela Tipo Curva Tripala de 1200 mm de Diámetro, Longitud Maxima de Eje: 2640 mm, Potencia del Motoreductor: 3 kW | L41: 167
